{
  "date": "2026-06-21",
  "prev_date": "2026-06-20",
  "trends": {
    "古风世情": {
      "new_count": 1,
      "dropped_count": 1,
      "new_books": [
        "我一介咸鱼，竟迎娶尚书嫡女"
      ],
      "dropped_books": [
        {
          "title": "我爹又升官了，这次是国丈",
          "intro": "（咸鱼+甜宠+轻喜不闹） 有谁听说过救人一命，还把一辈子搭进去的？ 花满满就是其中一个。 花满满这辈子只想当条咸鱼，找个符合她要求的婆家，苟完一生。 谁知，自从她及笄，她爹跟开了挂似的开始升官，从守城"
        }
      ],
      "top_risers": [
        {
          "title": "反派少年虽然病态，却实在是美味",
          "change": "+2"
        },
        {
          "title": "疯狗难驯？无妨，小郡主驯夫有方",
          "change": "+2"
        },
        {
          "title": "公主撒泼日常",
          "change": "+1"
        }
      ],
      "top_fallers": [
        {
          "title": "穿越老朱后宫，我开局冒充长平",
          "change": "-5"
        },
        {
          "title": "重生后不做续弦，他好友求娶了",
          "change": "-3"
        },
        {
          "title": "娇女不争，帝心自倾",
          "change": "-3"
        }
      ],
      "reads_growth": [
        {
          "title": "反派少年虽然病态，却实在是美味",
          "growth": "+8000"
        },
        {
          "title": "父皇驾崩后，我被迫监国",
          "growth": "+5000"
        },
        {
          "title": "公主撒泼日常",
          "growth": "+4000"
        }
      ],
      "summary": "**🔥 题材趋势** 古风世情呈现“女频向+强人设”风潮，主角设定从“咸鱼”、“疯批反派”到“事业型公主”百花齐放。核心驱动力从单纯的甜宠转向“先婚后爱”、“追妻火葬场”及“女帝/监国”的权力叙事，权谋基建元素显著增多。\n\n**📖 读者偏好** 读者高度青睐双洁、1v1与男主视角或强女主设定，“宠夫”、“驯夫”等互动明确的关系模式成热门标签。作品简介普遍强调“反差感”人设（如咸鱼配尚书、病娇反派美味）与高情绪价值冲突（囚禁、悔婚），爽点前置明显。\n\n**🆕 新上榜作品** 《我一介咸鱼，竟迎娶尚书嫡女》以16.6万在读空降榜首，主打“乐子人咸鱼男主×温柔宠夫女主”的轻松甜宠日常，精准戳中读者放松解压的阅读需求，开局即爆款。\n\n**📉 掉出榜单** 掉榜的《我爹又升官了，这次是国丈》同样涉及咸鱼甜宠元素，但可能因梗的冲击力与差异化不足被榜首新作取代，说明同类竞争下新颖人设和开篇钩子至关重要。\n\n**💡 值得关注** 《父皇他两辈子都在装》和《无归朝》代表的“父子救赎”与“亡国公主恨海情天”虐文向热度坚挺，显示在甜宠主流下，强情感张力的“重剧情”作品仍有稳固市场。"
    },
    "科幻末世": {
      "new_count": 2,
      "dropped_count": 2,
      "new_books": [
        "末世！她都修仙了你惹她干嘛",
        "末世，我吃好点怎么了？"
      ],
      "dropped_books": [
        {
          "title": "魂穿废土，我绑定了三个老公",
          "intro": "【废土+拾荒＋金手指＋男全洁】 论穿越者死亡方式大赏，谢寻悠被气死的！醒来魂穿废土人。 十八岁的原主面临“巨额”单身罚款，现在由谢寻悠继承，幸好她的小公寓跟来了～ 更好的消息，她谢寻悠不用缴纳单身罚款"
        },
        {
          "title": "穿越废土，异能大佬很低调",
          "intro": "农大毕业生沐紫，刚毕业就稀里糊涂的穿越到了废土一个同名同姓的十岁小姑娘身上，成了58号基地外城的…………"
        }
      ],
      "top_risers": [
        {
          "title": "我的水果出轨成性但超级好吃",
          "change": "+3"
        },
        {
          "title": "末世修罗场：车上都是我前男友",
          "change": "+2"
        },
        {
          "title": "救命穿越废土，开局通知我去选夫",
          "change": "+2"
        }
      ],
      "top_fallers": [
        {
          "title": "跑，还跑，再跑就把你吃掉",
          "change": "-3"
        },
        {
          "title": "末世天灾，截胡女主空间囤货养崽",
          "change": "-3"
        },
        {
          "title": "末世被抢异能后，魅惑皆为我臣服",
          "change": "-3"
        }
      ],
      "reads_growth": [
        {
          "title": "极寒末世，我跟着重生者买买买",
          "growth": "+1.0万"
        },
        {
          "title": "黑屋？美人NPC被末世暴徒豪夺",
          "growth": "+8000"
        },
        {
          "title": "电梯求生：我的天赋是长特殊蘑菇",
          "growth": "+6000"
        }
      ],
      "summary": "**🔥 题材趋势** 科幻末世赛道已全面“女频化”，主流题材从传统生存冒险转为“囤货+空间+重生/穿书”叠加“多男主雄竞/反派强制爱”的情感叙事。“零元购”、种田、养崽等日常元素与末世危机混搭成标配。\n\n**📖 读者偏好** 读者核心爽点在于“信息差碾压”与“资源安全感”，重生或穿越后利用先知优势疯狂囤货、截胡原女主机缘的桥段层出不穷。同时，“小黑屋”、“疯批”、“1vN修罗场”等标签表明，带感的人物情感博弈压倒了严酷环境描写。\n\n**🆕 新上榜作品** 《末世！她都修仙了你惹她干嘛》主打修仙×末世跨界混搭，女强冷脸萌设定新颖；《末世，我吃好点怎么了？》则聚焦万人迷女主在修罗场中享受主义生存，两者均反映末世言情化、爽文化的极致细分。\n\n**📉 掉出榜单** 掉榜作品《魂穿废土，我绑定了三个老公》和《穿越废土，异能大佬很低调》虽有“男全洁”、“空间”等标签，但可能因废土背景较为传统、核心冲突不够尖锐或书名钩子较弱，被更具反差感的作品挤出榜单。\n\n**💡 值得关注** 《电梯求生：我的天赋是长特殊蘑菇》和《我的水果出轨成性但超级好吃》以“无CP”设定和“上交国家”、“沙雕”等清奇脑洞稳定上榜，表明在主流“她力量”情感中，不走寻常路的创意设定仍能抢占细分市场。"
    },
    "游戏体育": {
      "new_count": 1,
      "dropped_count": 1,
      "new_books": [
        "排球：天才少女今天也在努力扣杀"
      ],
      "dropped_books": [
        {
          "title": "列车求生：她最擅长杀人了",
          "intro": "【女频，无cp+升级流+求生+游戏+多副本+武力值超高混乱中立女主】 　　全人类进入列车求生游戏，人人拥有初始技能，奚峋抽到一个诅咒： 　　宿命枷锁：意识清醒状态下，生命值不断减少。 　　什么都不干，"
        }
      ],
      "top_risers": [
        {
          "title": "海上求生：幸运满值有统界太子罩",
          "change": "+3"
        },
        {
          "title": "全民求生：别人吓哭，我在炖怪",
          "change": "+3"
        },
        {
          "title": "开局吞噬树召唤玩家横扫废土",
          "change": "+1"
        }
      ],
      "top_fallers": [
        {
          "title": "深海求生，我的天赋是牧鱼人？！",
          "change": "-2"
        },
        {
          "title": "无限求生游戏：每天都在抽取店铺",
          "change": "-1"
        },
        {
          "title": "公路求生：我召星际元帅成饭搭子",
          "change": "-1"
        }
      ],
      "reads_growth": [
        {
          "title": "重生成NPC我成了隐藏BOSS",
          "growth": "+6000"
        },
        {
          "title": "重生之花滑女王绝不认输",
          "growth": "+6000"
        },
        {
          "title": "爱我恨我，玩家榜前十全是我",
          "growth": "+5000"
        }
      ],
      "summary": "**🔥 题材趋势** 游戏体育分类由两大板块构成：“求生/无限流/游戏入侵”占据绝对主流，“电竞/传统体育”与“第四天灾”为两翼。“无CP+女强”与“系统/天赋”是核心标配，基建、种田、美食等副业元素深度融入求生框架。\n\n**📖 读者偏好** 读者偏爱开局即获SSS级或独特天赋的“爽文流”主角，倾向看女主利用规则或在生存夹缝中轻松制霸、颠覆世界观。“马甲”、“榜前皆我”等身份反转梗热度高，显示读者对口不对心、幕后黑手类叙事有强烈偏好。\n\n**🆕 新上榜作品** 《排球：天才少女今天也在努力扣杀》是少有的传统体育题材，以“天才少女+现实成长”路线闯入前20，说明在游戏分类中，写实向竞技成长故事若能触及国民运动，潜力不小。\n\n**📉 掉出榜单** 掉榜的《列车求生：她最擅长杀人了》，其“武力值超高混乱中立女主”设定虽强，但可能因书名和简介偏向极端刑杀风，在主打成长、种田和轻松炖怪的当前榜单氛围中，受众相对受限。\n\n**💡 值得关注** 《kpl：我想睡觉》和《网王：外挂是原神系统》代表粉丝向同人创作在榜单活跃，电竞（KPL）与经典IP（网王）结合系统外挂，仍能精准吸引特定圈层读者。"
    },
    "女频衍生": {
      "new_count": 2,
      "dropped_count": 2,
      "new_books": [
        "斩神：如我所书？行吧【",
        "还珠格格之知画晴儿双重生"
      ],
      "dropped_books": [
        {
          "title": "恶女综穿改命，目标荣华富贵",
          "intro": "高功能反社会人格的奚青猝死后被系统选中，穿成知名反派，帮她们逆天改命，成为人生赢家。 甄嬛传: 安陵容，华妃，宜修…… 延禧攻略: 纯妃，愉妃，继后…… 如懿传: 魏嬿婉，富察皇后，金玉妍…… 知否:"
        },
        {
          "title": "【港综】回到90年代和乌鸦拍拖",
          "intro": "【90年代+港综+古惑仔+港影】 1V1 HE 男主：陈天雄（乌鸦） 贺昭昭因救猫穿回90年香江绑定喵喵报恩系统。 开局面对古惑仔当街对砍被带去做笔录 出门就撞到乌鸦哥还下意识的捏了两把…… 啧，惹大"
        }
      ],
      "top_risers": [
        {
          "title": "王若弗成暴力郭皇后：仁宗，朕苦",
          "change": "+6"
        },
        {
          "title": "斩神：你管这叫度假世界？",
          "change": "+1"
        }
      ],
      "top_fallers": [
        {
          "title": "穿成影视剧里的那些妈",
          "change": "-3"
        },
        {
          "title": "综名著：万人迷名著世界生存实录",
          "change": "-2"
        },
        {
          "title": "HP：法王模拟器",
          "change": "-2"
        }
      ],
      "reads_growth": [
        {
          "title": "王若弗成暴力郭皇后：仁宗，朕苦",
          "growth": "+1.4万"
        },
        {
          "title": "斩神：你管这叫度假世界？",
          "growth": "+5000"
        },
        {
          "title": "HP：性转彼得如何拿下犬鹿狼",
          "growth": "+1000"
        }
      ],
      "summary": "**🔥 题材趋势** 头部作品高度集中于“综影视/影游同人”与“魂穿书/剧角色”，其中《斩神》和《微微一笑很倾城》等IP衍生文占据多席。设定上，“拆官配+改写意难平”和“性转+万人迷”成为主流，系统辅助或灵泉空间等金手指依然是标配。\n\n**📖 读者偏好** 读者偏爱“腹黑/女强+打脸”的爽感剧情，对“团宠”、“修罗场”和“甜文”有高需求。CP向偏好单一且明确的1v1关系（如KO、林七夜、西里斯），同时“黑原著主角团”或“新角色强势介入”的设定极具吸引力。\n\n**🆕 新上榜作品** 《斩神：如我所书？行吧【》融合了《斩神》与《崩坏》元素，以欢愉令使、种建木等脑洞吸睛。《还珠格格之知画晴儿双重生》则精准抓住“黑主角团”和“双重生复仇”热点，迎合了颠覆经典的需求。\n\n**💡 值得关注** 榜单竞争激烈，但《斩神》衍生文展现出极强生命力，同IP多部作品在榜。此外，《雪姨重生：原来依萍是我女儿》排名跃升，表明挖掘配角弧光、改写悲情命运的“反套路”经典重启仍大有可为。"
    },
    "玄幻言情": {
      "new_count": 0,
      "dropped_count": 0,
      "new_books": [],
      "dropped_books": [],
      "top_risers": [
        {
          "title": "穿成古早玄幻男主的路人族妹",
          "change": "+3"
        },
        {
          "title": "胎穿修仙界靠寻宝神通捡漏男女主",
          "change": "+2"
        },
        {
          "title": "杨戬要疯了：闺女天天想换爹",
          "change": "+1"
        }
      ],
      "top_fallers": [
        {
          "title": "资质平平，但顶美",
          "change": "-3"
        },
        {
          "title": "穿成耽美文女配男主全贴上来了",
          "change": "-2"
        },
        {
          "title": "明日方舟：岁炎录",
          "change": "-1"
        }
      ],
      "reads_growth": [
        {
          "title": "穿成古早玄幻男主的路人族妹",
          "growth": "+1.1万"
        },
        {
          "title": "胎穿修仙界靠寻宝神通捡漏男女主",
          "growth": "+4000"
        },
        {
          "title": "剑仙魔尊别舔女主！你妈被气活了",
          "growth": "+3000"
        }
      ],
      "summary": "**🔥 题材趋势** “穿书/同人+系统攻略”模式依然强势，但“负面状态转化”和“身份反转”成为新爆点，如开局被龙掳走、诈尸诅咒仇人。 “男全洁”（所有男性角色纯情）、“万人迷”和“1vn”高亮标签扎堆出现，女强男更强或男强女更强的对抗性关系备受青睐。\n\n**📖 读者偏好** 读者追求极致的“爽”与“苏”，偏好女主摆脱憋屈、快速打脸逆袭的剧情。身份设定上，隐藏大佬、满级回归或拥有逆天金手指的“废柴/路人”逆袭深受欢迎。同时，明确的“无CP”或“万人迷多箭头”成为两个极端热门的选项。\n\n**🆕 新上榜作品** 本期无新书冲入前20，榜单固化明显。这表明头部作品读者黏性高，新书突围难度增加，需要更具颠覆性的设定才能打破僵局。\n\n**💡 值得关注** “训儿/训夫”类爸妈文学（如《剑仙魔尊别舔女主！》）和“国风克苏鲁/第四天灾”（如《HP：法王模拟器》）等小众元素开始出现，虽排名短暂下滑，但其创新性可能成为后续潜力方向。另外，下沉市场对“易孕”、“生子”等题材的强需求在榜单尾部依然坚挺。"
    },
    "种田": {
      "new_count": 3,
      "dropped_count": 3,
      "new_books": [
        "真千金替嫁流放，空间囤货亿点点",
        "胎穿古代，在主角后面捡漏",
        "我靠拆快递在国子监后巷开小店"
      ],
      "dropped_books": [
        {
          "title": "穿越古代，八岁农女带妹闯天下",
          "intro": "【穿越架空+空间+无CP+异能+爽文】 　　末世异能者希卿月，身死穿越到了异世界成为一个八岁农家女，醒来之时三岁的妹妹刚被亲叔叔卖掉。 　　她拳打亲叔，去小镇救妹妹回来后果断找里正拟断亲文书。 　　身"
        },
        {
          "title": "开局分家？我有空间我怕啥！",
          "intro": "末世穿越到古代+空间+种田+家长里短 宋云汐是从末世穿越到了古代，一醒来才知道那个所谓的丈夫在成亲的第二日就去服了兵役，而很悲剧的是她肚子里还怀有孩子已经有两个月了，家里还要修了她，经过她的一翻周旋最"
        },
        {
          "title": "穿越喜当娘带娃捡漏囤货逃荒",
          "intro": "五一旅游遇暴风雨跌落山崖，赵晓芸一睁眼，竟穿成古代寡妇，还赠送了个儿子！ 穿越赠送捡漏金手指，可提示捡漏，可抽奖还赠送新手大礼包 意外的是儿子重生而来，上一世被人害死，重生归来只为护母周全，告知灾荒 "
        }
      ],
      "top_risers": [
        {
          "title": "穿成流放罪臣的恶毒妻",
          "change": "+4"
        },
        {
          "title": "食肆经营手札",
          "change": "+4"
        },
        {
          "title": "弹幕预知穿越，囤满仓粮肉过荒年",
          "change": "+3"
        }
      ],
      "top_fallers": [
        {
          "title": "末世穿成古代猎户女，我赢麻了！",
          "change": "-1"
        }
      ],
      "reads_growth": [
        {
          "title": "穿成流放罪臣的恶毒妻",
          "growth": "+4000"
        },
        {
          "title": "错嫁，和邻居糙汉的桃林秘事",
          "growth": "+3000"
        },
        {
          "title": "弹幕预知穿越，囤满仓粮肉过荒年",
          "growth": "+2000"
        }
      ],
      "summary": "**🔥 题材趋势** “流放/逃荒+空间/系统”的生存基建文是绝对主流，几乎包揽榜首。新上榜作品在空间设定上更加硬核，如“零元购搬空”和“囤货亿点点”，开局“弃妇/寡妇带娃”反差逆袭成为标配。\n\n**📖 读者偏好** 读者追求极致的“囤货安全感”和“生活化经营”爽感，偏好女主凭借美食医术或现代知识在乱世中立足。时代背景高度集中于古代架空，感情线多作为辅线，“苟到大结局”和“发家致富”是核心驱动力。\n\n**🆕 新上榜作品** 《真千金替嫁流放》叠加了替嫁、真千金和硬核医毒，爽点密集。《我靠拆快递在国子监后巷开小店》则另辟蹊径，以经营美食和国子监吃瓜的轻松日常为卖点，在沉重题材中脱颖而出。\n\n**💡 值得关注** “兽人”与“末世”元素交叉的《穿成丑雌兽后》等作品存在，但主流仍是古代背景。榜单中“穿书预知”、“弹幕预警”等外挂形式愈发多样，说明读者对主角信息优势的需求在持续细化。上升迅速的《食肆经营手札》表明纯美食经营向仍有稳定市场。"
    },
    "年代": {
      "new_count": 3,
      "dropped_count": 3,
      "new_books": [
        "丰腴美人小保姆，禁欲大佬沦陷了",
        "荒年随军，靠团购APP囤货躺赢",
        "七零搞错相亲对象破婆家九代单传"
      ],
      "dropped_books": [
        {
          "title": "绝嗣长官没儿子？小娇妻一胎三宝",
          "intro": "【娇软绿茶小白兔×霸道爹系军官】 七零+11岁年龄差+身高差+生子系统+甜分超标+生理性喜欢 陆瑾欢是家里幺女，她天真可爱，软糯乖巧，却被自私自利的姐姐介绍给了自己绝嗣的大伯哥。 丈夫不能生怎么办？ "
        },
        {
          "title": "一个山村女孩的一生",
          "intro": "一个山村女孩的短暂的一生，她经历过绝望和痛苦，也有享受过微弱的阳光和快乐，她在无人的角落哭过，在热闹的街头笑过…… （这是一个真实存在的故事，大山深处其中一个女孩短暂又悲哀的一生。）"
        },
        {
          "title": "七零炮灰女配，列车员的悠闲人生",
          "intro": "穿书七零，成为年代女频的女主的炮灰堂妹。 上一世，女主与男主背着她搞地下恋情，直到被推下海才幡然醒悟。 冤大头？ 被女主踩着机缘上位的炮灰？ 狗都不当。 重生到结婚前三天。 当场抓奸，手撕渣男，抢夺金"
        }
      ],
      "top_risers": [
        {
          "title": "小嘴叭叭姜糖，哑巴哈哈裴蘅",
          "change": "+9"
        },
        {
          "title": "小保姆和大领导",
          "change": "+5"
        },
        {
          "title": "八零神豪贵妇：儿砸别怕，娘来了",
          "change": "+2"
        }
      ],
      "top_fallers": [
        {
          "title": "东北往事之守活寡的女人",
          "change": "-1"
        }
      ],
      "reads_growth": [
        {
          "title": "娇软美人替嫁，冷面糙汉夜夜诱哄",
          "growth": "+1.1万"
        },
        {
          "title": "七零年代病佳人把偏执男哄迷糊了",
          "growth": "+9000"
        },
        {
          "title": "小嘴叭叭姜糖，哑巴哈哈裴蘅",
          "growth": "+9000"
        }
      ],
      "summary": "**🔥 题材趋势**  \n“先婚后爱+糙汉宠妻”仍是年代文绝对主流，书名强调“娇软美人”与“冷面糙汉/禁欲军官”的极致体型差和身份反差。同时，“丰腴美人”、“系统/空间”及“团宠学霸”成为热门叠加元素，金手指与日常温馨感并重。\n\n**📖 读者偏好**  \n读者偏爱双洁设定与强情感拉扯，要求女主具备清醒头脑或隐藏技能，不再满足于单纯娇弱人设。对七八十年代家长里短、随军生活及香江背景的奋斗故事有浓厚兴趣，追求细水长流的甜宠与打脸逆袭。\n\n**🆕 新上榜作品**  \n《丰腴美人小保姆》紧抓“保姆+禁欲大佬”的背德张力；《荒年随军》主打APP囤货躺赢，契合生存焦虑；《七零搞错相亲对象》突出暗恋成真与团宠逆袭，均踩中刚需爽点。\n\n**📉 掉出榜单**  \n《绝嗣长官没儿子》等三本掉榜，或因“一胎三宝”等元素略显陈旧，或纯悲剧叙事与山村纪实风，与当前追求的甜爽基调及强冲突节奏不符。\n\n**💡 值得关注**  \n“丰腴美人”与“香江贵妇”标签高频出现，暗示读者对丰腴身材审美及港风背景的接受度提升。另，《小嘴叭叭》类拒绝恋爱脑、助推父母离婚的清奇设定，显示出反套路需求。"
    },
    "现言脑洞": {
      "new_count": 1,
      "dropped_count": 1,
      "new_books": [
        "采集狩猎：年代大小姐星际求生"
      ],
      "dropped_books": [
        {
          "title": "穿成灵异文反派的恶毒女友",
          "intro": "楚薰穿成古早灵异文中的恶毒女配，拜金，虚荣，自私自利。 　　江肃供她吃喝，供她上学。 　　可她攀附了一个富二代后，便想抛弃江肃。 　　一个暴雨天，江肃匆忙赶来找女朋友的路上出了车祸…… 　　江肃怨念不"
        }
      ],
      "top_risers": [
        {
          "title": "我装失忆，死对头一心想骗我结婚",
          "change": "+3"
        },
        {
          "title": "宝宝换我攻略了！阴湿前任爽翻了",
          "change": "+3"
        },
        {
          "title": "胎穿星际，分配老公真香了！",
          "change": "+2"
        }
      ],
      "top_fallers": [
        {
          "title": "怪物入侵，但当爹又当妈",
          "change": "-4"
        },
        {
          "title": "恶毒女二被男主错认成女主后",
          "change": "-1"
        }
      ],
      "reads_growth": [
        {
          "title": "穿成财阀太子爷的作精前女友",
          "growth": "+4.4万"
        },
        {
          "title": "社恐小可怜穿成男主的捞子前女友",
          "growth": "+6000"
        },
        {
          "title": "惹上港圈大佬，小人鱼被亲哭了",
          "growth": "+6000"
        }
      ],
      "summary": "**🔥 题材趋势**  \n“穿书+前女友/女配反向操作”题材高度集中，多本围绕“捞金前女友”、“恶毒女配”觉醒后逆袭或摆烂展开。此外，“第二人称乙女”、“怪物入侵”及“星际分配婚姻”等脑洞分支涌现，设定越发大胆。\n\n**📖 读者偏好**  \n核心爽点是看女主在既定剧本中违规操作，颠覆男主掌控，拒绝虐文走向，要求双洁与男主真香打脸。读者热衷“潮男全洁”、万人迷但无雌竞的设定，追求极致的阅读安全感与女本位体验。\n\n**🆕 新上榜作品**  \n《采集狩猎：年代大小姐星际求生》融合女扮男装、年代穿越与星际生存，设定混搭感强，虽看似缝合怪，但精准满足了跨题材爱好者的猎奇心。\n\n**📉 掉出榜单**  \n《穿成灵异文反派的恶毒女友》掉榜，或因灵异+恶毒女配的传统组合在当前市场热度稍减，缺乏如“捞女”或“认错男主”等更具网感和情绪价值的新颖切入点。\n\n**💡 值得关注**  \n“认错攻略对象”与“用舍友照片网恋”等梗表明，由信息错位引发的雄竞修罗场仍是高流量密码。同时，《穿成动物后我萌翻全网》从人类视角切入动物文，是值得开辟的差异化赛道。"
    },
    "宫斗宅斗": {
      "new_count": 2,
      "dropped_count": 2,
      "new_books": [
        "表小姐今天出家了吗",
        "被镇北王掳走后，他偏执宠我入骨"
      ],
      "dropped_books": [
        {
          "title": "貌美小瞎子也要被强制爱吗",
          "intro": "【娇软貌美小瞎子×淡漠疏冷王爷】 双洁。 　　祖父死后，虞眠此生最大的执念，便是去寻那素未谋面的未婚夫。 　　这一路，险些沦为山匪的玩物，滚落陡坡时摔得浑身是伤。 　　救她的人叫陆忱。 　　她裹着他的"
        },
        {
          "title": "特工神医带武器空间称霸全天下",
          "intro": "[灵泉空间+武器库+神医+雇佣兵+杀手+跆拳道黑段+有仇必报+毒舌] 三十二世纪南宫玥表面身份只是一个每天挥霍的无知大小姐。 背后确是人人忌惮的杀手，神医，雇佣兵，她让谁死谁就得死。 只是……在一次执"
        }
      ],
      "top_risers": [
        {
          "title": "禁欲？宫宴夜，被病娇太子亲哭",
          "change": "+1"
        },
        {
          "title": "小狸奴诶，萌哉萌哉",
          "change": "+1"
        },
        {
          "title": "退休穿越，被迫拯救侯府全家",
          "change": "+1"
        }
      ],
      "top_fallers": [
        {
          "title": "四殿下又在发癫",
          "change": "-3"
        },
        {
          "title": "皇兄的金丝雀",
          "change": "-3"
        },
        {
          "title": "二嫁：君夺臣妻！贵妃冠宠后宫",
          "change": "-2"
        }
      ],
      "reads_growth": [
        {
          "title": "禁欲？宫宴夜，被病娇太子亲哭",
          "growth": "+1.7万"
        },
        {
          "title": "勾了有瘾世子！腰软，也得受着",
          "growth": "+1.2万"
        },
        {
          "title": "穿成炮灰皇后，和闺蜜扶暗卫登基",
          "growth": "+8000"
        }
      ],
      "summary": "**🔥 题材趋势**  \n宫斗宅斗榜已演变为强情感博弈场，病娇太子/世子类黑化强取豪夺题材占比极高，且多与女主觉醒、重生复仇绑定。同时，“女尊+雄竞”、“养崽无CP”及“闺蜜联手双穿书”等新方向异军突起。\n\n**📖 读者偏好**  \n读者极度渴求男主对女主的单向度疯狂占有与宠爱，追求“上位者低头”的情感落差。排斥雌竞，转向女主清醒搞事业或躺赢生娃的佛系路线，对女尊世界观及男性角色多样化的修罗场接受度飞涨。\n\n**🆕 新上榜作品**  \n《表小姐今天出家了吗》以“只想出家+为爱发疯男主”制造反差幽默；《被镇北王掳走后》主打身穿与强夺宠溺，强情节标签明显，两者均强化了男主极度纠缠的偏执力。\n\n**📉 掉出榜单**  \n《貌美小瞎子》的强制爱和《特工神医》的传统大女主设定掉榜，表明单纯生理弱势女主的虐恋，以及元素冗杂的万能女主，已无法满足当前对极致人物关系和纯粹情感主线的追求。\n\n**💡 值得关注**  \n榜单中《我碰到的女尊男子》与多本女尊文上榜，显示女尊接受度大幅提升。此外《四殿下又在发癫》等无CP养崽或亲情向文，在强烈言情信号中杀出，证明剧情向市场正在稳健抬头。"
    },
    "悬疑脑洞": {
      "new_count": 1,
      "dropped_count": 1,
      "new_books": [
        "盗墓：祈安卦"
      ],
      "dropped_books": [
        {
          "title": "盗墓：我在谢家刷画符熟练度",
          "intro": "六岁时，谢瑜终于记起了前世的记忆，发现自己来到了盗笔的世界。 意外察觉这个世界竟然存在灵气，符篆传承系统也终于启动，画符便可修炼。 谢瑜背靠系统，一边暗中推了谢雨臣一把，让谢家搭上国家线，彻底跳出九门"
        }
      ],
      "top_risers": [
        {
          "title": "我，编剧，灵气复苏",
          "change": "+8"
        },
        {
          "title": "穿进盗笔当采购，全九门都喊我靠",
          "change": "+2"
        },
        {
          "title": "盗墓：旮旯game终于更新了",
          "change": "+2"
        }
      ],
      "top_fallers": [
        {
          "title": "盗墓：给小哥看无邪的女仆装视频",
          "change": "-3"
        },
        {
          "title": "盗墓：她的马甲非人类",
          "change": "-2"
        },
        {
          "title": "全组织都知道，琴酒养了个叛徒",
          "change": "-2"
        }
      ],
      "reads_growth": [
        {
          "title": "穿进盗笔当采购，全九门都喊我靠",
          "growth": "+1.3万"
        },
        {
          "title": "我，编剧，灵气复苏",
          "growth": "+1.0万"
        },
        {
          "title": "盗墓笔记：原来是故人没死",
          "growth": "+8000"
        }
      ],
      "summary": "**🔥 题材趋势**  \n盗墓笔记同人占据绝对主导地位，占比超六成，且普遍融合系统、抽卡、万人迷等脑洞元素。此外，国运恐怖、灵气复苏、规则怪谈等诡异流与无限流题材亦有稳定表现，但热度远不及盗笔同人。\n\n**📖 读者偏好**  \n读者偏好强互动性与泥石流风格，如“弹幕剧透”、“反向攻略”等设定。主角多具备万人迷属性或强大金手指，CP向以All向、万人迷、男主切片居多，轻松搞笑与微恐氛围结合的作品更易上榜。\n\n**🆕 新上榜作品**  \n《盗墓：祈安卦》以“大数据穿越者+全知面板算命”切入，主打智谋与团宠，是盗笔同人中较新颖的设定，首周即上榜显示出读者对差异化视角的接受度。\n\n**📉 掉出榜单**  \n《盗墓：我在谢家刷画符熟练度》掉榜，其传统的“符篆修炼”路线在当下强剧情、强互动的脑洞趋势中略显常规，缺乏爆点。\n\n**💡 值得关注**  \n《我，编剧，灵气复苏》排名上升8位，其“编剧马甲+副本创作”的幕后黑手流玩法，代表了恐怖脑洞与系统文叠加的新方向，创作灵活性高。"
    },
    "古言脑洞": {
      "new_count": 3,
      "dropped_count": 3,
      "new_books": [
        "救命！穿成小狐狸被摄政王宠哭了",
        "没天赋？那也得科举！",
        "万人迷病美人她总是高不可攀"
      ],
      "dropped_books": [
        {
          "title": "打打打打，我家王妃有大病",
          "intro": "（评分刚出，后期会涨） 搞笑+系统+微沙雕+穿书+无厘头+虐渣+爱咋咋地 躁郁症+幻想症的疯批萧吉吉一睁眼，穿成丞相府没人疼的庶女，还被太后塞去寒王府，任务是暗杀昏迷一年、只剩一口气的活死人寒王。 谁"
        },
        {
          "title": "直播：病弱太子今天被废了吗？",
          "intro": "【直播+弹幕+清冷病美人+万人迷+系统+架空古代+基建】 季承阳在六岁的时候，看到了来自未来的弹幕，知道了自己未来因为身体病弱会被父母漠视，兄弟姐妹厌恶，臣子嫌弃。 因为是嫡长子，父母不得不捏着鼻子封"
        },
        {
          "title": "病弱太子李承乾，重生团宠万人迷",
          "intro": "【团宠+无cp】 李承乾上辈子被废贬庶，郁郁而终。 再睁眼，竟重生回幼年时，自己还是个粉雕玉琢的奶团子—— 【叮！已绑定「病弱白月光系统」】 【系统提示】：卿本瑶台月，谪落帝王家。生来体弱，却容华绝世"
        }
      ],
      "top_risers": [
        {
          "title": "小世子不想黑化，只想要爹爹抱",
          "change": "+5"
        },
        {
          "title": "我在大清当老六",
          "change": "+2"
        },
        {
          "title": "强制爱黑化合集",
          "change": "+2"
        }
      ],
      "top_fallers": [
        {
          "title": "谁懂啊！侯府庶女心声自动广播",
          "change": "-3"
        }
      ],
      "reads_growth": [
        {
          "title": "送爹入赘公主府，我被全府团宠了",
          "growth": "+1.9万"
        },
        {
          "title": "小世子不想黑化，只想要爹爹抱",
          "growth": "+1.1万"
        },
        {
          "title": "恶毒贵妃又又作死，弹幕教她躺赢",
          "growth": "+9000"
        }
      ],
      "summary": "**🔥 题材趋势**  \n“弹幕剧透”与“看戏（心声广播）”类设定持续火热，同时“萌宝/团宠+权谋/宫斗”的温情反差路线崛起，如小世子、伴生神兽等作品。帝王、摄政王等高位者“真香”式宠妻/宠娃仍是核心爽点。\n\n**📖 读者偏好**  \n读者偏好轻松搞笑的叙事基调，强力对抗外部威胁（如渣爹、反派）以守护家庭或实现躺赢。对历史人物的二次元化、日常化解读接受度高，萌宠、养崽等温情元素与打脸虐渣的爽感并重。\n\n**🆕 新上榜作品**  \n新上榜《救命！穿成小狐狸被摄政王宠哭了》融合末世大佬变萌宠的反差设定；《没天赋？那也得科举！》聚焦科举逆袭；《万人迷病美人她总是高不可攀》主打高姿态万人迷训犬，题材多元但均含有强身份反差。\n\n**📉 掉出榜单**  \n《直播：病弱太子今天被废了吗》、《病弱太子李承乾，重生团宠万人迷》掉榜，显示“病弱太子”类设定热度降温，读者可能审美疲劳。\n\n**💡 值得关注**  \n《小世子不想黑化，只想要爹爹抱》排名大幅上升，证明“萌娃感化冷血父亲”的亲情双向救赎模式具有强大市场号召力，是古言脑洞的情感张力新锚点。"
    },
    "快穿": {
      "new_count": 2,
      "dropped_count": 2,
      "new_books": [
        "快穿路人甲：又是保底的一天",
        "快穿之路人甲勾引别人男朋友上位"
      ],
      "dropped_books": [
        {
          "title": "被病娇强制爱了怎么办",
          "intro": "（病娇男主×娇软女主） 你被病娇盯上了。 逃不掉，躲不开。 那能怎么办？ 认命呗。 ——反正也逃不掉。 故事一：孤傲太子×不受宠表妹 故事二：狠辣无情校霸×转校乖乖女 故事三：未来姐夫×小透明妹妹 …"
        },
        {
          "title": "快穿：男主的恶毒白月光穿回来了",
          "intro": "（快穿+双洁+甜宠+1v1）（个别世界会有多个切片） 笨蛋娇纵女X醋精忠犬男 白月光。 顾名思义，是男主的心尖上的朱砂痣，求而不得的意难平。 好巧不巧，宁舒扮演的就是这么一个角色，还是个恶毒白月光。 "
        }
      ],
      "top_risers": [
        {
          "title": "甩了偏执前任后被迫回来哄夫",
          "change": "+4"
        },
        {
          "title": "【快穿】心机诱宠，上位攻略",
          "change": "+3"
        },
        {
          "title": "掠夺成瘾！",
          "change": "+3"
        }
      ],
      "top_fallers": [
        {
          "title": "厨神快穿，我在各个世界当大厨",
          "change": "-3"
        },
        {
          "title": "快穿：扮演坏种白月光",
          "change": "-3"
        },
        {
          "title": "快穿：小月亮上位指南",
          "change": "-2"
        }
      ],
      "reads_growth": [
        {
          "title": "心机勾引快穿：女主心上人归我了",
          "growth": "+1.9万"
        },
        {
          "title": "甩了偏执前任后被迫回来哄夫",
          "growth": "+1.3万"
        },
        {
          "title": "强制爱又怎样？老婆只能是我的呢",
          "growth": "+1.1万"
        }
      ],
      "summary": "**🔥 题材趋势**  \n“恶毒女配/路人甲上位”与“强制爱/病娇掠夺”是两大主流题材。雌竞、横刀夺爱、攻略原男主等“缺德”玩法盛行，道德感模糊的主角设定成为常态。\n\n**📖 读者偏好**  \n读者偏好无固定CP或男全洁设定，追求极致的情感拉扯与上位快感。单元剧形式下，世界背景多样化（古代、现代、星际），但核心爽点恒定：主角通过心机或魅力，取代原天命之子，收获偏爱与权力。\n\n**🆕 新上榜作品**  \n《快穿路人甲：又是保底的一天》以路人甲部门的多面手身份切入，主打日常与保底；《快穿之路人甲勾引别人男朋友上位》直接点明横刀夺爱，两者均聚焦于“路人甲”这一功能性定位的逆袭。\n\n**📉 掉出榜单**  \n《被病娇强制爱了怎么办》、《快穿：男主的恶毒白月光穿回来了》掉榜，或与题材老化有关，读者正寻求从“被强制爱”到“主动掠夺”的视角转变。\n\n**💡 值得关注**  \n榜单前两位均以30万左右在读断层领先，其共通点是“不单纯、不咸鱼”的心机主角，说明读者正在抛弃被动型女主，更青睐目标明确、主动出击的“猎人”形象。"
    },
    "青春甜宠": {
      "new_count": 1,
      "dropped_count": 1,
      "new_books": [
        "他把我从深山带走"
      ],
      "dropped_books": [
        {
          "title": "舍友网恋对象分币不掏给我爆金币",
          "intro": "雇佣兵大佬×纯欲舞蹈生 |双洁|掉马 | 扮演 沈岁安手头拮据，舍友嫌弃网恋对象一毛不拔、干脆直接把网恋账号甩给了她。 急需用钱的沈岁安索性接下，摆烂上阵接手网恋。 不就是网恋而已，不谈真心只搞钱，她"
        }
      ],
      "top_risers": [
        {
          "title": "贵族学院：小傻子也有修罗场吗？",
          "change": "+7"
        },
        {
          "title": "宝宝乖，轻点撩",
          "change": "+3"
        },
        {
          "title": "和高冷教授的争宠日常",
          "change": "+3"
        }
      ],
      "top_fallers": [
        {
          "title": "手拿女配剧本，男主能不能别亲了",
          "change": "-2"
        },
        {
          "title": "农村普女，但有万人迷光环",
          "change": "-2"
        },
        {
          "title": "我，怂且恶毒",
          "change": "-2"
        }
      ],
      "reads_growth": [
        {
          "title": "贵族学院：小傻子也有修罗场吗？",
          "growth": "+1.1万"
        },
        {
          "title": "漂亮女配觉醒，高冷校草后悔了",
          "growth": "+9000"
        },
        {
          "title": "宝宝乖，轻点撩",
          "growth": "+7000"
        }
      ],
      "summary": "**🔥 题材趋势** “全员恶人”或“万人迷”叠加“雄竞修罗场”成为绝对主流，强势取代传统1v1甜宠。兔精、普女、小傻子等“非常规”女主设定盛行，核心是通过反差感制造爽点与苏点。\n**📖 读者偏好** 读者极度渴求“被团宠”的情感代偿体验，偏爱女主在不知情或被动情况下魅力失控、引发男性角色集体“真香”和“雄竞”的剧情。男主“恋爱脑”、“卑微求爱”的设定持续吃香。\n**🆕 新上榜作品** 《他把我从深山带走》主打“寄人篱下+暗恋+久别重逢”的经典虐恋成长公式，在满屏快节奏修罗场中，凭细腻情感描写差异化突围。\n**📉 掉出榜单** 《舍友网恋对象分币不掏给我爆金币》可能因核心矛盾“钱”过于直白、缺乏情感拉扯张力，在甜宠区显得动机不纯而掉榜。\n**💡 值得关注** 《贵族学院：小傻子也有修罗场吗？》排名大幅跃升，证明“表面弱势但引多方争夺”的设定，在贵族学院背景下仍有极强的市场吸金力。"
    },
    "星光璀璨": {
      "new_count": 1,
      "dropped_count": 1,
      "new_books": [
        "娱乐圈之笨蛋美人她诱不自知"
      ],
      "dropped_books": [
        {
          "title": "港姐重生：大佬他又争又抢",
          "intro": "【年代港城港姐×香江地产大佬，一见钟情｜强取豪夺｜女明星上位记｜带娃变美系统】 拍风月电影出名毫无背景的过气港姐叶珍珍重生了。 重生回到了刚拿到港姐季军，被人坑骗签约的时候，好消息是大佬刚给她递橄榄枝"
        }
      ],
      "top_risers": [
        {
          "title": "直播：被豪门找回的我成了万人迷",
          "change": "+3"
        },
        {
          "title": "大馋丫头勇闯娱乐圈",
          "change": "+2"
        },
        {
          "title": "文娱：一首倒带开始统治娱乐圈",
          "change": "+2"
        }
      ],
      "top_fallers": [
        {
          "title": "穿到女男平等的世界后素人出道了",
          "change": "-3"
        },
        {
          "title": "黑道大佬重生偶像练习生后爆红了",
          "change": "-1"
        },
        {
          "title": "小奶团找妈妈，军区大院抢着要",
          "change": "-1"
        }
      ],
      "reads_growth": [
        {
          "title": "疯批假千金上恋综，霸总心率炸了",
          "growth": "+2.1万"
        },
        {
          "title": "大馋丫头勇闯娱乐圈",
          "growth": "+1.3万"
        },
        {
          "title": "养成系偶像回归，归来已满级",
          "growth": "+1.1万"
        }
      ],
      "summary": "**🔥 题材趋势** “直播”与“选秀”仍是两大核心造梦场景，“团播”、“八卦主播”等细分职业文兴起。作品普遍强调“颜值即正义”与“事业线逆袭”，无CP或男全洁成为重要卖点。\n**📖 读者偏好** 读者追求强烈的“养成感”和“打脸”爽感，乐于观看普通人（甚至穿书者）凭借美貌或才华，在镜头前从底层杀出重围。对“雄竞修罗场”和“神豪大哥”元素的需求依然旺盛。\n**🆕 新上榜作品** 《娱乐圈之笨蛋美人她诱不自知》精准切入“笨蛋美人+训狗文学+道德感低”的风口，用极具反差和背德感的人设吸引眼球。\n**📉 掉出榜单** 《港姐重生》可能因年代文背景与主流的即时直播、娱乐圈爽文节奏存在门槛，加之设定偏传统商战言情，在快节奏榜中显得慢热而读者流失。\n**💡 值得关注** 多部作品以“女穿男”或无CP视角切入，如《女穿男，万人迷从颜值拉满开始》，显示部分读者开始寻求更自由的代入视角和纯粹的事业爽感。"
    },
    "女频悬疑": {
      "new_count": 1,
      "dropped_count": 1,
      "new_books": [
        "盗笔模拟器：玩家她不是人"
      ],
      "dropped_books": [
        {
          "title": "【神夏】她是一条小金鱼",
          "intro": "安娜·布兰特cp麦考夫·福尔摩斯 麦考夫发现221隔壁的女人太奇怪了，没有亲人，没有朋友，没有恋人，生活的像是个隐形人，还有着一身秘密。 这太适合监视夏洛克了，事实也是如此，安娜比预想中的聪明，能干，"
        }
      ],
      "top_risers": [
        {
          "title": "和张起灵分手后，他要炸了青铜门",
          "change": "+2"
        },
        {
          "title": "综盗墓：男神排排坐",
          "change": "+1"
        },
        {
          "title": "让让，挡我杀人了",
          "change": "+1"
        }
      ],
      "top_fallers": [
        {
          "title": "盗墓：变成守墓兽，被小哥投喂",
          "change": "-2"
        },
        {
          "title": "离婚后，我出马了",
          "change": "-1"
        }
      ],
      "reads_growth": [
        {
          "title": "退役即巅峰：女兵王横扫刑侦队",
          "growth": "+5000"
        },
        {
          "title": "盗墓：读心后，汪家卧底在线发疯",
          "growth": "+4000"
        },
        {
          "title": "她从地狱来，证罪",
          "growth": "+2000"
        }
      ],
      "summary": "**🔥 题材趋势** 《盗墓笔记》同人占据半壁江山，形成以“黑瞎子x原创女主”为核心的固定言情模式。原创悬疑则多与重生、系统、刑侦元素结合，强调“以暴制暴”的爽快感。\n**📖 读者偏好** 读者核心需求是将惊悚刺激的冒险与甜蜜恋爱结合，在同人世界里与高人气角色（尤其黑瞎子、张起灵）发展感情。原创文中，“兵王/杀手”型大女主与刑警联手破案是热门组合。\n**🆕 新上榜作品** 《盗笔模拟器：玩家她不是人》以“非人玩家（奶牛猫）”切入盗笔世界，用“反向保姆文”和“疯癫团宠”的新鲜设定成功吸引眼球。\n**📉 掉出榜单** 《【神夏】她是一条小金鱼》因作为英美剧同人，其IP受众基础与番茄主流的盗墓、刑侦题材读者匹配度低，难以形成集群效应而自然掉出。\n**💡 值得关注** 盗笔同人赛道极度拥挤，但“黑瞎子”相关CP热度断层领先，几乎成为新书上榜的“财富密码”。原创悬疑主角需具备更强的主动性和暴力制裁能力才能突围。"
    },
    "职场婚恋": {
      "new_count": 2,
      "dropped_count": 2,
      "new_books": [
        "胖妹不配？毒舌总裁吻到我腿软",
        "假破产后一家三口生活指南"
      ],
      "dropped_books": [
        {
          "title": "七年难孕，再婚后一胎双宝",
          "intro": "白鹿和周泽结婚七年一直要不上孩子，不能生育的检查单也跟了白鹿七年，再深的情感也被现实的压力消磨掉，为了传宗接代，周泽选择和白鹿离婚再娶，麻木的白鹿接受主任的相亲，和主任不能生育的儿子闪婚搭伙过日子，可"
        },
        {
          "title": "听潮阁：哥哥们的小尾巴",
          "intro": "（不喜这个设定勿进！！想到哪就写到哪了！有不一样的地方就是私设！） “你是说饶子有个妹妹！” “那是我们大家的妹妹！” 突如其来的妹妹会和他们发生哪些奇妙的化学反应呢？"
        }
      ],
      "top_risers": [
        {
          "title": "娶了落魄大小姐，硬汉沦为老婆奴",
          "change": "+1"
        },
        {
          "title": "重逢后，野警官每天都想复合",
          "change": "+1"
        }
      ],
      "top_fallers": [
        {
          "title": "闪婚搭子，联手专治奇葩家人",
          "change": "-2"
        },
        {
          "title": "浮礁",
          "change": "-1"
        },
        {
          "title": "东北老太嫁台北，斗豪门，护闺女",
          "change": "-1"
        }
      ],
      "reads_growth": [
        {
          "title": "他的生理性喜欢",
          "growth": "+9000"
        },
        {
          "title": "乙代：你是我命中注定的妻子",
          "growth": "+8000"
        },
        {
          "title": "二十二岁，但儿子十八",
          "growth": "+3000"
        }
      ],
      "summary": "**🔥 题材趋势** 职场婚恋榜单以“先婚后爱”和“高岭之花下神坛”为核心题材，强调身份反差带来的戏剧张力，如女设计师与厅级领导、警局画像师与刑警队长。同时，“双洁”、“甜宠”仍是标配安全标签，但纯甜腻设定稍有回落。\n\n**📖 读者偏好** 读者偏爱带有强烈职业身份冲突和日常暧昧拉扯的故事，男主多为禁欲、理性型精英，女主则具有专业技能或独特审美。近期“治愈向”、“救赎感”和“成年人拉扯”的细腻描写更受欢迎，如第14名《浮礁》。\n\n**🆕 新上榜作品** 《胖妹不配？毒舌总裁吻到我腿软》主打“现实改编+毒舌霸总”，题材下沉；《假破产后一家三口生活指南》聚焦“破产后家长里短”，突显生活化婚恋的潜力。\n\n**📉 掉出榜单** 传统虐文和复杂设定题材热度下降，《七年难孕》因题材沉重、情绪压抑而掉榜；《听潮阁：哥哥们的小尾巴》因简介混乱、核心卖点不清而读者流失。\n\n**💡 值得关注** 第4名《二十二岁，但儿子十八》以“年龄倒置+穿越子代”的新颖设定异军突起，预示“反套路亲情/奇幻设定”可能成为该分类新的流量密码。"
    },
    "豪门总裁": {
      "new_count": 1,
      "dropped_count": 1,
      "new_books": [
        "和重欲大佬联姻：老婆，过来亲我"
      ],
      "dropped_books": [
        {
          "title": "网恋掉马，被重欲金主亲懵了！",
          "intro": "【占有欲Max大佬×奶黄包小骗子】双洁 【宝宝，好想你】 【宝宝，拍照片视频可以吗】 【宝宝，今天穿小猫装…】 【……】 许芙缺钱，在网上聊了个“冤大头”。 转账不眨眼，语音视频不露脸，人傻钱多还好哄"
        }
      ],
      "top_risers": [
        {
          "title": "对她不屑一顾的权贵们，全沦陷了",
          "change": "+2"
        },
        {
          "title": "错把闪婚老公的微信当成AI网恋",
          "change": "+1"
        },
        {
          "title": "穿成男主室友的恶毒女友",
          "change": "+1"
        }
      ],
      "top_fallers": [
        {
          "title": "疯批佛子又贪又嗔又痴",
          "change": "-2"
        },
        {
          "title": "弟弟们好凶！！！明明我才是大哥",
          "change": "-1"
        },
        {
          "title": "京圈小公主抢我男友，我当她继母",
          "change": "-1"
        }
      ],
      "reads_growth": [
        {
          "title": "偷闺蜜照片网恋财阀继承人沦陷了",
          "growth": "+2.8万"
        },
        {
          "title": "穿成男主室友的恶毒女友",
          "growth": "+2.2万"
        },
        {
          "title": "强制爱：恶毒女配被病娇反派亲哭",
          "growth": "+1.1万"
        }
      ],
      "summary": "**🔥 题材趋势** 榜单由“技术性错位”题材强势主导，如“误认AI”、“冒充身份”、“穿书自救”，利用信息差制造密集笑点和反转。传统“强取豪夺”式总裁文逐渐被“上位者卑微”、“追妻火葬场”的叙事替代，男主设定普遍为位高权重但恋爱脑或占有欲极强的反差形象。\n\n**📖 读者偏好** 读者极度青睐“穿书恶毒女配逆袭”和“先婚后爱、日久生情”的爽甜路线。作品简介多采用“钩子式”场景（如《错把闪婚老公微信当AI》），强调男主从傲慢到沦陷的过程，“双洁”依然是硬通货，但“病娇”、“疯批”等暗黑人设混合甜宠也成为新增长点。\n\n**🆕 新上榜作品** 《和重欲大佬联姻：老婆，过来亲我》紧抓“联姻+上位者先拒后宠”这一爆款公式，主打“真香定律”。\n\n**📉 掉出榜单** 《网恋掉马，被重欲金主亲懵了！》因同质化严重的“掉马金主”梗和冗长简介，在激烈的头部竞争中失去优势。\n\n**💡 值得关注** “科技感”或“规则性”误会成为新引擎，如第1名《错把闪婚老公微信当成AI网恋》，将传统身份错认与AI热点结合，制造极强的新鲜感和戏剧效果，建议关注类似现实与虚拟交错的设定。"
    },
    "民国言情": {
      "new_count": 1,
      "dropped_count": 1,
      "new_books": [
        "潜伏：苦海无涯，殊途同归"
      ],
      "dropped_books": [
        {
          "title": "谍战：我的动物军团杀疯了",
          "intro": "乱世狼烟，日寇横行。 孤女禾苗，觉醒万兽之主系统。 鼠潜地道，鸦探长空； 猫狗盯梢，蜂群破阵； 毒蛇隐杀，步步为营。 以鸟兽为耳目，以虫蛇为刀锋。 隐于市井，搅动谍战迷局； 孤身抗敌，踏平倭寇凶焰。 "
        }
      ],
      "top_risers": [
        {
          "title": "幽龛锁岁岁，孤城寄新月",
          "change": "+4"
        },
        {
          "title": "谍影清道夫，我专杀鬼子不站队",
          "change": "+1"
        }
      ],
      "top_fallers": [
        {
          "title": "人间正道是沧桑：四十年来家国",
          "change": "-2"
        },
        {
          "title": "谍战：我竟是敌方顶级女领导",
          "change": "-1"
        },
        {
          "title": "捂不热的军婚，她不要了",
          "change": "-1"
        }
      ],
      "reads_growth": [
        {
          "title": "倒闭首选：在青铜门开店",
          "growth": "+3000"
        },
        {
          "title": "幽龛锁岁岁，孤城寄新月",
          "growth": "+1075"
        },
        {
          "title": "谍影清道夫，我专杀鬼子不站队",
          "growth": "+1000"
        }
      ],
      "summary": "**🔥 题材趋势** 谍战与言情深度融合，民国分类不再是单纯军阀豪门爱恨，而是“特工”、“潜伏”、“女强”、“家国情怀”占据超高比重。同时，“同人衍生”（以《潜伏》角色为蓝本）成为一股不可忽视的创作力量，占据多席。\n\n**📖 读者偏好** 读者追求强女主、专业智斗和考究的民国质感。无CP或专注事业的独立女性形象（如清道夫杀手、女间谍）极受欢迎，感情线多为强强对抗或乱世守护。偏爱冷门、高阶职业设定（如画像师、密码破译），且作品简介需清晰有力。\n\n**🆕 新上榜作品** 《潜伏：苦海无涯，殊途同归》作为同人作品上榜，证明此类围绕知名IP“填补遗憾”或“再创作”的写法有稳定受众。\n\n**📉 掉出榜单** 《谍战：我的动物军团杀疯了》因系统+金手指设定偏向“爽文”套路，与当前民国区追求硬核谍战和现实质感的氛围相悖而掉榜。\n\n**💡 值得关注** 第2名《倒闭首选：在青铜门开店》是罕见的“盗墓+系统+日常流”跨界融合，提示平台在传统民国分类下，对复合型或冒险奇谭类“年代文”有进一步包容和拓展的空间。"
    }
  }
}