{
  "date": "2026-05-20",
  "prev_date": "2026-05-19",
  "trends": {
    "古风世情": {
      "new_count": 0,
      "dropped_count": 0,
      "new_books": [],
      "dropped_books": [],
      "top_risers": [
        {
          "title": "失忆后，表小姐她移情别恋了",
          "change": "+1"
        },
        {
          "title": "将门有朵病娇花",
          "change": "+1"
        },
        {
          "title": "穿越成魏征的小女儿",
          "change": "+1"
        }
      ],
      "top_fallers": [
        {
          "title": "远古，神赐五百年我延续母系社会",
          "change": "-3"
        },
        {
          "title": "快穿：权臣的娇媚女配成了心尖宠",
          "change": "-1"
        },
        {
          "title": "本崽说了算，你有意见？",
          "change": "-1"
        }
      ],
      "reads_growth": [
        {
          "title": "重生：双姝媚骨，撩翻权臣覆江山",
          "growth": "+8000"
        },
        {
          "title": "失忆后，表小姐她移情别恋了",
          "growth": "+8000"
        },
        {
          "title": "今生不误君",
          "growth": "+7000"
        }
      ],
      "summary": "**🔥 题材趋势** 古风世情榜呈现“权谋甜宠”与“重生逆袭”双雄并立格局。榜单头部作品如《穿成开国皇帝病弱早逝的好大儿》、《重生：双姝媚骨，撩翻权臣覆江山》均将“重生/穿越+抱大腿/复仇”作为核心框架，说明读者对此类“预知未来、规避风险、逆天改命”的爽感模式认可度极高。\n\n**📖 读者偏好** 当前读者偏爱“强强互动”与“极致人设”。女性向“她力量”崛起，“娇媚女主x疯批权臣”、“病弱白月光x偏执皇帝”等张力组合是流量密码。同时，《本崽说了算，你有意见？》等幼崽团宠无CP文、《剿匪剿到亲闺女，丞相爹爹崩溃了》等沙雕亲情文也稳定占据席位，显示市场对轻松、治愈向内容的持续需求。\n\n**🆕 新上榜作品** 本期无全新面孔上榜，榜单固化现象明显，头部作品护城河深厚，新书突围难度较大。\n\n**📉 掉出榜单** 本期无作品掉出榜单，整体排名呈微调状态，仅《远古，神赐五百年我延续母系社会》因题材相对宏大冷门，下降3位，但仍在榜内。\n\n**💡 值得关注** TOP1《穿成开国皇帝病弱早逝的好大儿》以“无CP团宠”定位独占鳌头，说明“亲情羁绊+白月光”模式可有效取代传统言情套路，为创作提供新思路。同时，《土匪娘子带崽进京》等融合“萌宝+认亲”元素的作品，展现出长线吸粉潜力。"
    },
    "科幻末世": {
      "new_count": 1,
      "dropped_count": 1,
      "new_books": [
        "末世降临：我却成了无症状感染者"
      ],
      "dropped_books": [
        {
          "title": "末世：穿成大男主的娇弱妹妹",
          "intro": "【末世＋丧尸＋变异动植物】【1v1娇软治愈系妹宝x战力爆表帅哥】 叶熙和穿进一本以末世为背景的大男主小说。 好消息：男主非常疼爱她这个妹妹。 坏消息：她死了。 叶熙和准备好了苟命，却发现……剧情走向怎"
        }
      ],
      "top_risers": [
        {
          "title": "魂穿废土，我绑定了三个老公",
          "change": "+1"
        },
        {
          "title": "国运荒野：满级真千金带飞全龙国",
          "change": "+1"
        },
        {
          "title": "满级女巫在星际封神",
          "change": "+1"
        }
      ],
      "top_fallers": [
        {
          "title": "抱紧妖孽反派大腿：末世游戏外挂",
          "change": "-1"
        },
        {
          "title": "够格的队友才有资格做合格的伴侣",
          "change": "-1"
        },
        {
          "title": "你在做饭呢？我在炼制药剂",
          "change": "-1"
        }
      ],
      "reads_growth": [
        {
          "title": "末世降临，被六个审判官强制收容",
          "growth": "+1.2万"
        },
        {
          "title": "魂穿废土，我绑定了三个老公",
          "growth": "+2000"
        },
        {
          "title": "抱紧妖孽反派大腿：末世游戏外挂",
          "growth": "+1000"
        }
      ],
      "summary": "**🔥 题材趋势** 末世题材已从传统“丧尸生存”全面转向“多元设定融合”。榜单TOP1《末世降临，被六个审判官强制收容》是“异能+收容控制”的典型；《末世捡个小傻子，反派大佬宠上天》则融合“甜宠+失忆”元素。核心趋势是：末世仅为背景板，真正驱动的内核是“情感关系”或“独特金手指”。\n\n**📖 读者偏好** 读者偏好“极限拉扯的强制爱”与“躺赢爽文”。TOP1凭借“1VN、全洁、极限拉扯”等标签在在读量上断层领先，证明情感张力是第一驱动力。同时，“空间囤货+养崽”、“满级大佬带飞国家队”等安心种田或极致爽文依旧稳健，反映出读者在末日背景下对“安全感”和“爽感”的双重追求。\n\n**🆕 新上榜作品** 新上榜《末世降临：我却成了无症状感染者》，以无穿越重生异能的“校园群像+无症状感染”差异化设定突围，说明在超能力泛滥的当下，另类生存困境仍有市场。\n\n**📉 掉出榜单** 《末世：穿成大男主的娇弱妹妹》掉榜，其“娇弱治愈”的常规设定在当前追求更强冲突和爽感的快节奏市场中，竞争力不足。\n\n**💡 值得关注** “废土拾荒”题材（如《魂穿废土，我绑定了三个老公》）正悄然流行，相比传统都市末世，废土背景更具生存压力感，易于展开新社会规则与人际关系构建，值得持续观察。"
    },
    "游戏体育": {
      "new_count": 3,
      "dropped_count": 3,
      "new_books": [
        "全民种田：国家霸榜求生游戏",
        "我在KPL当全职野王",
        "隐藏玩家：我在求生游戏偷偷升级"
      ],
      "dropped_books": [
        {
          "title": "游戏降临：开局氪爆游戏充值上限",
          "intro": "【无CP+重生+生存+末日+游戏】 全球灾变，游戏成真。 重生归来的林夏发现回到《生存游戏》即将降临蓝星。 不作他想，第一时间她便开启氪金之路，输入支付密码输到手抽筋。 再一次面对游戏降临后的困境，她"
        },
        {
          "title": "从无限流回归后，我杀穿末日",
          "intro": "【满级大佬屠杀新手村 + 末日游戏 + 无cp + 爽文】 宁岑寂从无限系统买断“卖身契”归来，存款够挥霍一辈子，只想在原生世界喝茶养猫混吃等死。 下一秒，血月当空，【蚀日乐园】全域通知响彻地球，这个"
        },
        {
          "title": "顿顿鱼肉，你管这叫公路求生？",
          "intro": "【重生+囤货+无CP+经营+系统+公路求生】 第一次穿越到公路求生，林芝满怀热血，最后嘎得默默无闻。 眼睛一闭一睁，竟然回到了被传送前100分钟！ 一百分钟能干什么？ 能在商场来一次大型采购！ 尤其是"
        }
      ],
      "top_risers": [
        {
          "title": "海上求生：开局觉醒黑暗料理家",
          "change": "+3"
        },
        {
          "title": "全民求生：提前三小时登录",
          "change": "+2"
        },
        {
          "title": "龙岛异兽：逍遥游",
          "change": "+2"
        }
      ],
      "top_fallers": [
        {
          "title": "海上求生，魅力点满真的有用吗？",
          "change": "-1"
        }
      ],
      "reads_growth": [
        {
          "title": "安全屋：榜一她衣橱又又又又满啦",
          "growth": "+3000"
        },
        {
          "title": "网王：外挂是原神系统",
          "growth": "+1000"
        },
        {
          "title": "海上求生：开局觉醒黑暗料理家",
          "growth": "+305"
        }
      ],
      "summary": "**🔥 题材趋势**\n游戏体育分类榜高度集中于「求生游戏」大类型，形成“全民求生+囤货基建”的绝对主流。其中细分场景以海洋、公路、沙漠等环境求生为主，高频绑定“女强+无cp+系统/天赋开局”设定，种田、美食、安全屋等副标签扎堆。\n\n**📖 读者偏好**\n读者口味偏向“独立成长爽文”，偏好女主靠欧皇天赋或特殊职业实现轻松碾压的资源积累爽感，排斥感情线依赖。金手指"
    },
    "女频衍生": {
      "new_count": 2,
      "dropped_count": 2,
      "new_books": [
        "黄亦玫重生：这次我选孟宴臣",
        "红楼：黛玉的驯夫之道！"
      ],
      "dropped_books": [
        {
          "title": "小欢喜：我季杨杨亲弟弟",
          "intro": "陆时安觉得老天爷在跟他开玩笑。 毕业两年，月薪五千，合租隔断间，每天被甲方和组长来回碾压。朋友圈里的同学兄弟们，出国的出国，读研的读研，继承家业的继承家业，结婚的结婚。他加班到深夜回到十平米的出租屋，"
        },
        {
          "title": "斩神：我靠王者系统拯救遗憾",
          "intro": "【斩神+王者+all向+团宠+拆原著CP+私设如山】评分刚出，还会长大滴~ 安禾平平淡淡的生活了十八岁，突然有一天发现自己是穿越的！还是穿越高危的斩神世界！！ 好消息：她有了金手指！还是她最爱的王者农"
        }
      ],
      "top_risers": [
        {
          "title": "甄嬛传：大小姐驾到，通通闪开",
          "change": "+3"
        },
        {
          "title": "影视：不知道啊！反正人生很曼妙",
          "change": "+2"
        },
        {
          "title": "四合院：我是傻柱大师兄",
          "change": "+2"
        }
      ],
      "top_fallers": [
        {
          "title": "斩神：我靠歌声拯救时间之神",
          "change": "-4"
        },
        {
          "title": "渡莲：我把哪吒调成了病娇",
          "change": "-2"
        },
        {
          "title": "【暮光】燃烧",
          "change": "-2"
        }
      ],
      "reads_growth": [
        {
          "title": "甄嬛传：大小姐驾到，通通闪开",
          "growth": "+1.1万"
        },
        {
          "title": "穿成小燕子：只做乾隆掌中娇宠女",
          "growth": "+1.0万"
        },
        {
          "title": "锦叶良缘",
          "growth": "+5000"
        }
      ],
      "summary": "**🔥 题材趋势** 经典影视同人占据绝对主导，尤以《甄嬛传》为核心，前20名中出现了4本相关衍生作品。此外，综影视快穿、红楼同人、以及设定反转（如性转、女帝）也是热门方向。\n**📖 读者偏好** 读者偏爱“预知剧情”带来的信息差爽感，以及携带系统、高超幸运值等金手指轻松破局。女主形象普遍要求具备清醒、强势、拒绝内耗的特质，对“背德感”或攻略特定男性角色的设定有明显兴趣。\n**🆕 新上榜作品** 两本新书均带有“重生选择”或“驯服”标签，一本题材融合了热播现代剧角色，另一本是经典红楼IP的纯爱设定，显示出老IP叠加新视角仍有吸引力。\n**📉 掉出榜单** 掉榜作品主要来自现代都市剧同人及特定动漫同人，相比之下，其“穿越成配角”的套路可能不如皇后、贵妃等身份自带冲突感和爽感。\n**💡 值得关注** “女帝+性转男后宫”和“考公人穿越三生三世”等设定，在传统同人中开辟了极强反差感的新路径，显示出读者对反套路创新的高接受度。"
    },
    "玄幻言情": {
      "new_count": 2,
      "dropped_count": 2,
      "new_books": [
        "穿成龙傲天情敌，每天被迫修罗场",
        "女配已就位，薅主角羊毛会上瘾"
      ],
      "dropped_books": [
        {
          "title": "截胡机缘万倍返还，女配偷偷成仙",
          "intro": "（分刚出，会暴涨）[无cp+腹黑+系统+老六+穿书+爽文+横推+偏女强+升级成长] 叶无双穿书成为名剑山庄嫡女，本以为能够躺平摆烂开启咸鱼生活，没曾想才穿越，即将被原书未来的天命女帝百般羞辱，然后要被"
        },
        {
          "title": "穿成废灵根：捡的夫君个个是大佬",
          "intro": "猝死穿越成玄灵大陆废灵根，凤颜歌麻了。 在这个以女为尊，强者为尊的世界，没灵根，还没男人要? 被胞妹同族欺负，还要被生母当做弃子扔掉。 她不想做弃子，她要逆袭变强！ 她有系统，娶夫就能变强，修炼资源那"
        }
      ],
      "top_risers": [
        {
          "title": "这位修士我们人妖殊途啊",
          "change": "+3"
        },
        {
          "title": "怎奈她一身反骨，就爱给众神添堵",
          "change": "+2"
        },
        {
          "title": "资质平平，但顶美",
          "change": "+2"
        }
      ],
      "top_fallers": [],
      "reads_growth": [
        {
          "title": "这位修士我们人妖殊途啊",
          "growth": "+1.2万"
        },
        {
          "title": "什么，那是阐教大师姐？！",
          "growth": "+9000"
        },
        {
          "title": "怎奈她一身反骨，就爱给众神添堵",
          "growth": "+8000"
        }
      ],
      "summary": "**🔥 题材趋势** 洪荒封神背景、穿书成恶毒女配/路人逆袭是两大主流。近期，以“反骨”、“沙雕”、“反向操作”解构传统虐文或龙傲天叙事的风格抬头明显。\n**📖 读者偏好** 读者热衷“万人迷”或“团宠”属性女主，强调女主即便资质平平也能凭美貌或独特魅力吸引众多强大男性角色。对“黑化”、“阴湿”型男主和“强取豪夺”情节有稳定需求。\n**🆕 新上榜作品** 新上榜作品强化了“修罗场”与“薅主角羊毛”的爽点，一本是穿成男主情敌的冲突设定，另一本则是直接抢夺原女主所有机缘的重生女配路线，竞争更加直白。\n**📉 掉出榜单** 掉榜作品一本为“截胡机缘万倍返还”，另一本为“捡的夫君个个是大佬”，可能因为“横推”或“靠他人”的设定不如女主主动制造修罗场或直接掠夺来得更有代入感和爽感。\n**💡 值得关注** “龙傲天父皇”与“白鹤童子”等作品在用男性向或正剧叙事打开女频市场，这种“无cp/亲情向”的稳健成长路线，满足了部分读者对深度剧情而非单纯感情线的需求。"
    },
    "种田": {
      "new_count": 1,
      "dropped_count": 1,
      "new_books": [
        "养父母恶毒？不伺候！带灵泉分家"
      ],
      "dropped_books": [
        {
          "title": "穿成暴躁肥妇，极品儿子们遭殃了",
          "intro": "【种田】＋【无CP】＋【无金手指】＋【发家致富】＋【家长里短】＋【美食】＋【轻松搞笑】 很幸运，江洛洛穿越了。 很不幸，江洛洛穿越到了极品肥妇身上，二百多斤的体重，奸懒馋滑全占了。 四个儿女也都是极品"
        }
      ],
      "top_risers": [
        {
          "title": "穿越古代，八岁农女带妹闯天下",
          "change": "+1"
        },
        {
          "title": "分家，继母渣爹跪求我回家",
          "change": "+1"
        },
        {
          "title": "开局抄家，我带太孙去逃荒",
          "change": "+1"
        }
      ],
      "top_fallers": [
        {
          "title": "穿成娇软白月光霸王龙它又爱又恨",
          "change": "-1"
        },
        {
          "title": "恶毒前妻再就业，汴京第一妙厨娘",
          "change": "-1"
        },
        {
          "title": "被强嫁傻夫！我靠词条捡满朝权臣",
          "change": "-1"
        }
      ],
      "reads_growth": [
        {
          "title": "穿越古代，八岁农女带妹闯天下",
          "growth": "+4000"
        },
        {
          "title": "刚穿就被卖？我带家人断亲逃荒去",
          "growth": "+3000"
        },
        {
          "title": "悍妻进门：扶起一屋软骨头",
          "growth": "+2000"
        }
      ],
      "summary": "**🔥 题材趋势**\n穿越种田仍是绝对主流，且高度融合“分家断亲+虐渣打脸”叙事。高频元素集中于空间/系统等金手指，并出现向兽世、逃荒、基建等细分方向拓展的明显趋势，同质化竞争加剧。\n\n**📖 读者偏好**\n读者高度偏爱“开局逆袭”的强爽感与发家致富的成长线"
    },
    "年代": {
      "new_count": 1,
      "dropped_count": 1,
      "new_books": [
        "七零拒守活寡，嫁偏执狂军官"
      ],
      "dropped_books": [
        {
          "title": "重生：搬空首富家底去北大荒",
          "intro": "上一世，我是江南顾家的大小姐顾晚。 特殊时期一来，家被抄、人被批斗，爷爷奶奶被逼死，三个哥哥流放惨死，我冻毙在北大荒的雪地里。 睁眼，我竟重生回到了风波前！ 风声已紧，断了联系的二叔一家等着落井下石，"
        }
      ],
      "top_risers": [
        {
          "title": "七零：不受宠怎样，偏偏我最争气",
          "change": "+3"
        },
        {
          "title": "六零小丧包天天被妖孽首长挂腰上",
          "change": "+3"
        },
        {
          "title": "冒充堂姐相亲，我骗到部队首长",
          "change": "+2"
        }
      ],
      "top_fallers": [
        {
          "title": "亲哥重生后，真千金回归了",
          "change": "-1"
        }
      ],
      "reads_growth": [
        {
          "title": "九零：婴语满级，全豪门求我带娃",
          "growth": "+1.5万"
        },
        {
          "title": "村女吴秀丽",
          "growth": "+1.3万"
        },
        {
          "title": "随父入赘后，假娇软成家属院团宠",
          "growth": "+1.3万"
        }
      ],
      "summary": "**🔥 题材趋势** 年代文持续深耕“穿书/重生+军婚/糙汉”强设定，并涌现“换亲/替嫁”等身份错位开局。异能、系统等金手指与家长里短、发家致富主线深度绑定，呈现“大女主搞事业”与“甜宠养成”并行的格局。\n**📖 读者偏好** 读者偏爱女主摆脱极品原生家庭、靠先知或技能逆袭的爽感叙事，尤其青睐“军官硬汉X娇软/清醒美人”的反差CP。带娃、婆媳关系等生活流情节与事业线结合紧密，爽感与温情兼备。\n**🆕 新上榜作品** 《七零拒守活寡，嫁偏执狂军官》融合“追妻火葬场”与“换嫁”热梗，精准切入读者对反转打脸和极致力占有欲的喜好。\n**📉 掉出榜单** 《重生：搬空首富家底去北大荒》因“北大荒”艰苦背景下假千金设定略显沉重，与当前“先婚后爱”“随军”等即时甜爽的主流偏好略有脱节。\n**💡 值得关注** “年代+萌宝/婴语”元素迅速升温，如Top4作品将满级婴语与豪门团宠结合，开辟了家庭温情与反差萌的新赛道，值得重点关注。"
    },
    "现言脑洞": {
      "new_count": 1,
      "dropped_count": 1,
      "new_books": [
        "全员重生：小傻子依旧乖巧"
      ],
      "dropped_books": [
        {
          "title": "当男频文大反派早死的亲妹觉醒后",
          "intro": "【全息游戏+游戏入侵+金手指大开+无脑爽+重生觉醒+无cp】 【封面是模版封，禁嗑腐】 江梨月死后才知道，自己所在的世界居然是一本男频游戏文。而她，是里面出场不过几次，就因为被霸凌自杀而亡的炮灰。 她"
        }
      ],
      "top_risers": [
        {
          "title": "哥！你再当舔狗我就跟黄毛带球跑",
          "change": "+4"
        },
        {
          "title": "孕妻重生，京圈太子爷他偏执溺爱",
          "change": "+2"
        },
        {
          "title": "游戏变美系统，我是两百斤女野王",
          "change": "+1"
        }
      ],
      "top_fallers": [],
      "reads_growth": [
        {
          "title": "社恐小可怜穿成男主的捞子前女友",
          "growth": "+6.4万"
        },
        {
          "title": "亲妈归来，五个逆子请接驾",
          "growth": "+2.4万"
        },
        {
          "title": "穿成灵异文反派的恶毒女友",
          "growth": "+9000"
        }
      ],
      "summary": "**🔥 题材趋势** 脑洞文全面爆发，“废土哨兵强制爱”、“游戏变美”等现实世界叠加超凡设定的“反差流”最受追捧。同时，虐文拯救、系统任务、豪门团宠等经典框架持续输出，但均需搭载“社恐捞女”、“婴语”等极致人设标签。\n**📖 读者偏好** 读者偏爱“反差感”与“网感梗”密集型作品，“双洁”不再绝对，修罗场、多男主、强制爱等元素接受度高。“无CP搞事业”或“有CP嗑糖”界限分明，萌宝、基建、上交国家等新颖切入点吸量显著。\n**🆕 新上榜作品** 《全员重生：小傻子依旧乖巧》聚焦全家重生背景下的“追妹火葬场”与团宠救赎，情绪拉扯强，精准击中读者对虐渣和亲情治愈的双重期待。\n**📉 掉出榜单** 《当男频文大反派早死的亲妹觉醒后》作为“游戏入侵”题材，在当前“强制爱”与“系统变美”等情感驱动型脑洞文洪流中，可能因设定偏传统而暂时退出。\n**💡 值得关注** “向上社交”类题材如《绑定带货系统》和《误入阴间群聊后》，以任务形式连接超自然与现实资源，展现了脑洞文嫁接社会议题和职业元素的强大潜力。"
    },
    "宫斗宅斗": {
      "new_count": 2,
      "dropped_count": 2,
      "new_books": [
        "假千金被满京权贵疯狂觊觎",
        "咸鱼嫁纨绔"
      ],
      "dropped_books": [
        {
          "title": "穿入1vn文，恶毒女配只想活命",
          "intro": "(刚出分，后续会涨)一次意外，谢安念穿进了一本古早1vn玛丽苏文里，成了里面的恶毒女配。 为了活下去，她开始主动贴近男主，只为傍大腿。 本想借势苟到大结局，却没料到，真正的女主出场后，本该被女主吸引的"
        },
        {
          "title": "媚骨之资！尔等皆为裙下臣",
          "intro": "1vn 架空 她只想寻一个自由身，却发现遇到的每一个男人，都想做她的牢笼。 他们每个人都想让她留在自己身边。"
        }
      ],
      "top_risers": [
        {
          "title": "挚友之妻",
          "change": "+4"
        },
        {
          "title": "改嫁竹马兄长后，竹马回来了！",
          "change": "+4"
        },
        {
          "title": "重生宠妃不强制爱后，陛下他急了",
          "change": "+4"
        }
      ],
      "top_fallers": [
        {
          "title": "兄长，你敢娶女主我就跟山匪私奔",
          "change": "-6"
        },
        {
          "title": "被迫入宫后，太子他赖上我了",
          "change": "-1"
        },
        {
          "title": "大明：朱元璋老来得女，力大无穷",
          "change": "-1"
        }
      ],
      "reads_growth": [
        {
          "title": "万人觊觎的假公主被拉下高台后",
          "growth": "+2.1万"
        },
        {
          "title": "挚友之妻",
          "growth": "+1.8万"
        },
        {
          "title": "良陈美錦",
          "growth": "+7000"
        }
      ],
      "summary": "**🔥 题材趋势** 宫斗宅斗赛道“重生/觉醒”已成标准配置，并分化出两大主流：“攻略帝王/权臣”的强取豪夺风，与“假千金/庶女”周旋于多个权贵间的万人迷修罗场。男主“疯批病娇”属性泛滥，权谋让位于激烈的情感拉扯。\n**📖 读者偏好** 读者对“强取豪夺”和“多角雄竞”的接受度极高，尤其青睐女主看似娇弱被动，实则清醒算计、游刃有余掌控关系的“钓系美人”设定。双洁与男全洁是这类题材的硬性要求。\n**🆕 新上榜作品** 《假千金被满京权贵疯狂觊觎》集齐假千金、读心/预知、阴湿奴隶等爆款元素，主打身份危机下的强制爱，顺应当前“万人迷”与“修罗场”风潮。\n**📉 掉出榜单** 《穿入1vn文，恶毒女配只想活命》等同类型作品因过多关注“生存任务”，在当下“强制爱”与“情感博弈”浓度急剧提升的环境中，可能显得冲突张力不足。\n**💡 值得关注** “轻松向”宫斗宅言开始冒头，如《哀家不想听》、《皇家街溜子》以打工、街溜子等现代梗解构宫斗，预示了在高虐主流外，沙雕减压的新风尚可能成为新增长点。"
    },
    "悬疑脑洞": {
      "new_count": 2,
      "dropped_count": 2,
      "new_books": [
        "盗墓：祈安卦",
        "沙海：喂！你们别变异啊！"
      ],
      "dropped_books": [
        {
          "title": "氪金养崽后，哑巴张反向投喂我",
          "intro": "【盗墓同人+脑洞+双向救赎+极度护短+治愈甜宠+爆笑爽文】 林月的破手机里多了个卸不掉的像素游戏。 游戏里有个戴兜帽的小哑巴，天天在雪山挨冻，在古墓放血，孤零零地惨得让人心疼。 母爱泛滥的林月一咬牙，"
        },
        {
          "title": "盗墓：被九门盯上，真的逃不掉啊",
          "intro": "沈墨被一群神经病盯上了。 一个漂亮的穿女装吸引他的注意力， 一个笑面虎天天恐吓他， 一个戴墨镜的总是半夜偷袭，说一些有的没的， 他跑了，但又被抓了回来。 无邪：“还跑吗？” 黑瞎子：“其实读取蛇的费洛"
        }
      ],
      "top_risers": [
        {
          "title": "无限：拒绝和boss贴贴",
          "change": "+5"
        },
        {
          "title": "盗笔大舞台，有命你就来！",
          "change": "+3"
        },
        {
          "title": "精神病也要在惊悚游戏谈恋爱",
          "change": "+3"
        }
      ],
      "top_fallers": [
        {
          "title": "盗笔：穿成万奴王后她摆烂了",
          "change": "-2"
        },
        {
          "title": "漂亮小可怜在暗黑童话被疯狂觊觎",
          "change": "-1"
        },
        {
          "title": "盗笔：我真不是张家人，真的！",
          "change": "-1"
        }
      ],
      "reads_growth": [
        {
          "title": "天幕亮了，放的却是九叔电影",
          "growth": "+1000"
        },
        {
          "title": "盗墓，是玩家不是精分吖",
          "growth": "+1000"
        },
        {
          "title": "无限：拒绝和boss贴贴",
          "growth": "+1000"
        }
      ],
      "summary": "**🔥 题材趋势** 盗墓同人占据半壁江山，暗黑童话、无限流与天幕观影体形成次级热点，脑洞多围绕“已知IP二创+系统/穿书”展开。\n**📖 读者偏好** 万人迷、女嬷向、无CP或甜宠标签吸量明显，主角“柔弱/摆烂/非人”等反差人设与“病娇/疯批”男主配对成主流。\n**🆕 新上榜作品** 《盗墓：祈安卦》融合算命与全知面板，《沙海：喂！你们别变异啊！》主打系统＋黑莲花盲女，均以新颖设定切入盗笔宇宙。\n**📉 掉出榜单** 掉榜作品同为盗墓甜宠向，说明同质化内容竞争激烈，读者更青睐强反转、马甲或特殊能力设定。\n**💡 值得关注** 盗墓同人虽泛滥但仍有细分缺口，“反套路NPC”“精分玩家”等视角带来新鲜感，暗黑向1vN与女强猎杀型女主在榜尾蓄力。"
    },
    "古言脑洞": {
      "new_count": 0,
      "dropped_count": 0,
      "new_books": [],
      "dropped_books": [],
      "top_risers": [],
      "top_fallers": [],
      "reads_growth": [
        {
          "title": "沈世子，您真是做男做女都精彩啊",
          "growth": "+9000"
        },
        {
          "title": "摄政王的白月光亡妻死而复生了",
          "growth": "+5000"
        },
        {
          "title": "抄家流放？战王妃携空间先搬为敬",
          "growth": "+4000"
        }
      ],
      "summary": "**🔥 题材趋势** 换装/婴语/生子系统等金手指密集，“带娃/奶娘/团宠”与“伪装神女/天幕曝光”形成两条主线，清穿、逃荒种田稳居刚需。\n**📖 读者偏好** 爽文节奏与无CP/万人迷并行，女强+空间、读心纨绔卷疯等“反差逆袭”受捧，男主视角独子文亦有一席之地。\n**🆕 新上榜作品** 本期无新上榜，榜单固化严重，头部作品在读断层明显（最高28.7万），说明古言脑洞头部护城河较高。\n**📉 掉出榜单** 无掉榜，前二十排名完全静止，读者行为趋于沉淀，新书突围难度大，需强设定或引流破局。\n**💡 值得关注** “婴语十级”系列化趋势明 - 显，多本同选题高位运转；世子男扮女装、妖妃反向强国等抽象爆款保持热度，值得深挖。"
    },
    "快穿": {
      "new_count": 1,
      "dropped_count": 1,
      "new_books": [
        "快穿：男主不要欺负恶毒女配了！"
      ],
      "dropped_books": [
        {
          "title": "心机女配万人迷，扮乖装茶勾男主",
          "intro": "[快穿+女配上位+微万人迷+女主超会演+1V1] 姜岁杳同时绑定了海.棠系统和女配逆袭系统，一个任务是得到男主的爱，一个任务是得到男主的人 姜岁杳：原女主，抱歉，你的男主以后是我的了 ❀ 世界一：姐姐"
        }
      ],
      "top_risers": [
        {
          "title": "快穿：女主宝宝她实在貌美",
          "change": "+4"
        },
        {
          "title": "木头万人迷，但真路人【快穿】",
          "change": "+1"
        },
        {
          "title": "被病娇强制爱了怎么办",
          "change": "+1"
        }
      ],
      "top_fallers": [
        {
          "title": "快穿：心机女配勾引上位",
          "change": "-3"
        },
        {
          "title": "快穿：又又又被大佬叼回窝了",
          "change": "-2"
        },
        {
          "title": "恶毒女配她千娇百媚",
          "change": "-2"
        }
      ],
      "reads_growth": [
        {
          "title": "被病娇强制爱了怎么办",
          "growth": "+1.0万"
        },
        {
          "title": "恶毒女配她千娇百媚",
          "growth": "+6000"
        },
        {
          "title": "快穿：女主宝宝她实在貌美",
          "growth": "+6000"
        }
      ],
      "summary": "**🔥 题材趋势** 万人迷路人/娇软女主×病娇男配仍为主流，男配视角、纯兽甜宠、生子部门等打开支线，女配拜金/心机恶女上位文密集。\n**📖 读者偏好** 1vN与1v1双洁并重，强调“男全洁”“男主沦陷”“吃醋修罗场”；精致利己、从不吃亏的女主更契合当下情绪。\n**🆕 新上榜作品** 《快穿：男主不要欺负恶毒女配了！》以呆萌美人+病娇1v1回归，替代掉榜的心机女配单一向，亮点在“男主主动配合剧本”。\n**📉 掉出榜单** 掉榜作品为女配万人迷+1V1，同质化下未出新意，被更直接甜宠或反差虐渣反超。\n**💡 值得关注** “真路人”“冷脸萌”等淡人设开始挑战传统万人迷，男频女配训狗与炮灰逆袭稳中有升，快穿渐从纯恋爱拓至事业线叙事。"
    },
    "青春甜宠": {
      "new_count": 1,
      "dropped_count": 1,
      "new_books": [
        "被校霸前任囚禁，觉醒后不敢分手"
      ],
      "dropped_books": [
        {
          "title": "穿成欺负美强惨男主的恶毒女配后",
          "intro": "一睁眼，乔笙穿成欺负美强惨男主的恶毒女配。 原书中，跟男主相依为命的恶毒女配怕男主出人头地抛弃她，作天作地搅黄男主一个又一个人生机遇，一边心安理得吸他的血一边跟别人嘲笑他是她的狗。 男主飞黄腾达回归豪"
        }
      ],
      "top_risers": [
        {
          "title": "穿成恶毒女配后我只想当白富美",
          "change": "+2"
        },
        {
          "title": "回到豪门，我比比格还能闯祸",
          "change": "+1"
        },
        {
          "title": "穿成男主的哭唧唧青梅前女友",
          "change": "+1"
        }
      ],
      "top_fallers": [
        {
          "title": "哥，你再舔女主我就跟黄毛私奔",
          "change": "-2"
        },
        {
          "title": "橘咖",
          "change": "-2"
        },
        {
          "title": "病弱美人只想搞学习续命",
          "change": "-1"
        }
      ],
      "reads_growth": [
        {
          "title": "大小姐雇我替她和太子爷网恋",
          "growth": "+3.4万"
        },
        {
          "title": "回到豪门，我比比格还能闯祸",
          "growth": "+8000"
        },
        {
          "title": "宝宝乖，再亲一口好不好",
          "growth": "+6000"
        }
      ],
      "summary": "**🔥 题材趋势** 觉醒、恶女、穿书与反套路成为绝对主流，“后悔流”、“觉醒流”正在取代传统傻白甜。同时，以《病弱美人只想搞学习续命》为代表的“病弱/美强惨+救赎”题材稳定占据高位，显示出读者对强情感张力的持续需求。\n**📖 读者偏好** “双洁”仍被多数头部作品作为重要卖点强调，显示核心读者对感情纯粹度有硬性要求。人设上，“钓系女主”、“痞帅/拽哥男主”以及“男二上位”、“追妻火葬场”等经典模式结合新梗（如替身网恋）更受青睐。\n**🆕 新上榜作品** 《被校霸前任囚禁，觉醒后不敢分手》融合了“觉醒”和“囚禁”这类微强制禁忌元素，满足读者寻求刺激与女主反杀的双重期待，同时“糙汉忠犬”人设也提供新鲜感。\n**📉 掉出榜单** 《穿成欺负美强惨男主的恶毒女配后》的掉榜，或因其核心矛盾（欺负男主）仍停留在传统“恶毒女配”框架，在当下“不雌竞+女主自我觉醒”的大潮中略显陈旧。\n**💡 值得关注** “穿书+系统”已成为基础设定，如何在经典模板上叠加新颖的微创新（如《大小姐雇我替她和太子爷网恋》的“外包网恋”梗），是突围关键。"
    },
    "星光璀璨": {
      "new_count": 1,
      "dropped_count": 1,
      "new_books": [
        "直播还债，糙汉室友现身后我爆火"
      ],
      "dropped_books": [
        {
          "title": "热搜爆了！影后和她的电竞隐婚夫",
          "intro": "全网热搜轰然爆雷。 影视歌三期出道的人气影后许知瑶，被曝早已隐婚生子。 全网哗然，议论漫天。 所有人都在好奇，究竟是谁，能娶到前途无量的实力派影后。 真相揭开，全网瞬间嘲讽一片。 对方竟是电竞圈的林屿"
        }
      ],
      "top_risers": [
        {
          "title": "团播：神豪系统是我榜一",
          "change": "+3"
        },
        {
          "title": "电子幽灵在主播文里当神豪",
          "change": "+3"
        },
        {
          "title": "AI垄断文娱，我带神曲杀穿全球",
          "change": "+1"
        }
      ],
      "top_fallers": [
        {
          "title": "让你荒野求生，你一根树枝斩野猪",
          "change": "-8"
        },
        {
          "title": "老婆你怎么梦男如此多【万人迷】",
          "change": "-1"
        }
      ],
      "reads_growth": [
        {
          "title": "小宝宝找妈妈，全网抢着要领养",
          "growth": "+1.3万"
        },
        {
          "title": "穿成炮灰作曲人，我靠神曲杀疯了",
          "growth": "+2000"
        },
        {
          "title": "团播：神豪系统是我榜一",
          "growth": "+2000"
        }
      ],
      "summary": "**🔥 题材趋势** “直播”、“团播”、“选秀”与“文娱事业线”高度捆绑，形成“曝光即爽点”的核心模式。神豪、系统、重生/穿书是女主获取资源与能力的三大核心金手指。\n**📖 读者偏好** 读者热爱“扮猪吃虎”与“马甲文”，偏好女主用真本事（如神颜、神曲、实力）打破偏见，实现美貌与才华的双重碾压。 “万人迷”属性是核心爽点来源，但侧重事业打脸和逻辑闭环。\n**🆕 新上榜作品** 《直播还债，糙汉室友现身后我爆火》，主打“纯欲天花板”与“糙汉”的极致体型差和出租屋同居暧昧，抓住了读者对现实感和性张力的需求，是“直播+”题材的又一细分切口。\n**📉 掉出榜单** 《热搜爆了！影后和她的电竞隐婚夫》的出局，可能因为“隐婚”梗已是过去式，当前趋势更偏向女主在公众视野下通过职业能力直接征服观众和舆论场。\n**💡 值得关注** 《文娱我的分身在台前，本体在幕后》的“分身”设定和《AI垄断文娱，我带神曲杀穿全球》的“文化降维打击”概念，代表了文娱题材寻求差异化的新方向。"
    },
    "女频悬疑": {
      "new_count": 1,
      "dropped_count": 1,
      "new_books": [
        "盗墓：从宝可梦世界走到盗笔世界"
      ],
      "dropped_books": [
        {
          "title": "学霸少女勇闯贵族学校",
          "intro": "【多男主➕玛丽苏➕雄竞➕单箭头】 全员豪门的顶级贵族学校，转来一个一无所有的公费生，全校等着看她笑话。 众人嘲讽她寒门低配、痴心高攀。 殊不知，低调学霸藏锋芒，赛场封神，碾压世家天才，凭实力逆天翻盘！"
        }
      ],
      "top_risers": [
        {
          "title": "刑侦甜妹，在变态修罗场杀疯了",
          "change": "+2"
        },
        {
          "title": "和张起灵分手后，他要炸了青铜门",
          "change": "+1"
        },
        {
          "title": "续写第十二年",
          "change": "+1"
        }
      ],
      "top_fallers": [
        {
          "title": "成为张起灵小姨，我把所有人带跑",
          "change": "-2"
        },
        {
          "title": "凶案现场，我这个美少女能看见鬼",
          "change": "-1"
        },
        {
          "title": "盗墓：我在盗笔杀穿主线",
          "change": "-1"
        }
      ],
      "reads_growth": [
        {
          "title": "盗墓：潘家园有个沈老板",
          "growth": "+1.1万"
        },
        {
          "title": "和张起灵分手后，他要炸了青铜门",
          "growth": "+3000"
        },
        {
          "title": "凶案现场，我这个美少女能看见鬼",
          "growth": "+2000"
        }
      ],
      "summary": "**🔥 题材趋势** “盗墓笔记同人”占据半壁江山，且多与原创女主、CP黑瞎子或张起灵等经典角色深度绑定，形成“下墓+恋爱”的固定模式。另一大趋势是“刑侦+超自然能力”，女主通过看见鬼魂、听见万物声音、闻到凶手等金手指破案。\n**📖 读者偏好** 读者对“变态/阴湿/疯批”男主人设接受度极高，尤其在“贵族学院”或“修罗场”背景下，追求极致的、危险的性张力。同时，独立强大的女主人设（如刑侦专家、法医）也备受追捧。\n**🆕 新上榜作品** 《盗墓：从宝可梦世界走到盗笔世界》是典型的“综漫/综题材”乱炖穿越，其脑洞大开、世界观融合的写法吸引了大批寻求新奇的读者，显示了盗墓同人赛道内部迭代创新的压力。\n**📉 掉出榜单** 《学霸少女勇闯贵族学校》的掉榜，说明在悬疑分类下，纯“玛丽苏+雄竞”若无强悬疑主线或更高能的人设（如全员疯批、真杀人魔），竞争力将相对不足。\n**💡 值得关注** “专业+悬疑”模式仍在进化，如《合约夫人是刑侦顾问》将“契约婚姻”与“刑侦顾问”身份结合，带来双重反差期待，是跨界融合的成功案例。"
    },
    "职场婚恋": {
      "new_count": 2,
      "dropped_count": 2,
      "new_books": [
        "我被老公骗去缅北",
        "寻子三十年，儿子竟是公司保安"
      ],
      "dropped_books": [
        {
          "title": "查小美不渣，只是没心没肺",
          "intro": "【女主特殊体质不自知、天然渣属性不自知、无贞洁观、脑洞虚构、不喜勿入】 查小美智力有轻微缺陷，不影响生活，就是学习不行。 她迟钝一根筋，忠于自己。 在不影响她的前提下，她很善解人意，孝顺温柔，尊重任何"
        },
        {
          "title": "表白被拒，一觉醒来和男神有了娃",
          "intro": "（评分刚出，后期会涨！）双洁＋男主外科医生×女主颜控，精神状态不详 林雯，18岁的青春美少女，一觉醒来穿到了十年后…… 　　还和拒绝过自己的男神，有了一个五岁的儿子。 　　—— 　　林雯正在跟暗恋的男"
        }
      ],
      "top_risers": [
        {
          "title": "重生后我退了所有单身群",
          "change": "+6"
        },
        {
          "title": "嗜赌村妇，死后只值两万",
          "change": "+5"
        },
        {
          "title": "和刑警队长先婚后爱了",
          "change": "+2"
        }
      ],
      "top_fallers": [],
      "reads_growth": [
        {
          "title": "穿成恶毒女配和落魄男主拼婚养娃",
          "growth": "+4000"
        },
        {
          "title": "重生后我退了所有单身群",
          "growth": "+3000"
        },
        {
          "title": "中奖后我被糙汉军官宠上天",
          "growth": "+2000"
        }
      ],
      "summary": "**🔥 题材趋势** 现实题材强势崛起，缅北诈骗、寻子认亲等社会热点被迅速转化为高冲突故事；同时，中奖逆袭、军婚糙汉等甜爽设定依然是流量基本盘，表明市场兼容强冲突与治愈两种极端。\n**📖 读者偏好** 读者喜爱“女主清醒独立、男主恋爱脑”的模式，情感线讲究“进度快、长嘴、双洁”，并追求快速的情绪释放：既要虐渣打脸的爽感，也要成年人不言爱的极致拉扯。\n**🆕 新上榜作品** 《我被老公骗去缅北》《寻子三十年，儿子竟是公司保安》携浓厚现实议题上榜，以“地狱开局”和强烈情感冲击取胜，验证了猎奇+复仇的吸量法则。\n**📉 掉出榜单** 《查小美不渣…》《表白被拒…》因设定伦理争议或叙事过于平淡跌出榜单，说明读者对逻辑合理性与故事钩子的要求日益提升。\n**💡 值得关注** 《中奖后我被糙汉军官宠上天》高居榜首，显示“中奖+军婚”的致富安定文组合极具市场。“缅北”题材接连出现，或成细分新风口。"
    },
    "豪门总裁": {
      "new_count": 1,
      "dropped_count": 1,
      "new_books": [
        "被分手的男友是另一本书男主"
      ],
      "dropped_books": [
        {
          "title": "男友冷冰冰，提分手他却破防了",
          "intro": "【双洁/同居日常/小甜文】 　　林望夕发现自己是一本狗血文里的恶毒假千金。 　　剧情告诉她，她还剩半的时间，然后就会莫名其妙的死掉。 　　真千金回来后，她无处可去。 　　没想到，最后却是她强迫来的落魄"
        }
      ],
      "top_risers": [
        {
          "title": "穿书：开局睡了男主",
          "change": "+3"
        },
        {
          "title": "许我明珠",
          "change": "+1"
        },
        {
          "title": "糟糕，漂亮娇气包是炮灰女配",
          "change": "+1"
        }
      ],
      "top_fallers": [
        {
          "title": "冒名顶替真千金后，嫁入了豪门",
          "change": "-1"
        },
        {
          "title": "禁止侵入",
          "change": "-1"
        },
        {
          "title": "宝贝乖，让我亲一下",
          "change": "-1"
        }
      ],
      "reads_growth": [
        {
          "title": "网恋掉马，被重欲金主亲懵了！",
          "growth": "+2.1万"
        },
        {
          "title": "许我明珠",
          "growth": "+1.1万"
        },
        {
          "title": "宝贝乖，让我亲一下",
          "growth": "+1.0万"
        }
      ],
      "summary": "**🔥 题材趋势** 核心仍是“重生复仇”与“强取豪夺”，但叙事视角微创新，如《睁眼！太子爷的恶毒女友重生了》让恶毒女配主导，或《大佬圈养的小白兔跑路了》强调女性反杀，旧瓶装新酒效果显著。\n**📖 读者偏好** “男洁”（处男）成高频标签，读者对男德要求苛刻。同时，“上位者为爱当狗”、“雌竞变雄竞”是最大爽点，故事多走先虐后甜或纯恨拉扯路线，旨在提供极致的情感代偿。\n**🆕 新上榜作品** 《被分手的男友是另一本书男主》凭借穿书设定中“身世错位”的戏剧性入榜，这表明融合穿书与亲情线，在纯恋爱文中开辟轻团宠视角，仍是有效突围方式。\n**📉 掉出榜单** 《男友冷冰冰…》因剧情节奏平淡、书名与“追妻火葬场”预期不符被取代，说明在信息流中，必须用尖锐开篇和强设定留住读者。\n**💡 值得关注** 冒名顶替、带球跑等经典梗依旧能打，但《哥，你再当舔狗…》等训哥文学异军突起，预示家庭内部权力重构带来的爽感正成为新增长点。"
    },
    "民国言情": {
      "new_count": 1,
      "dropped_count": 1,
      "new_books": [
        "穿回四十年代逃荒去上海"
      ],
      "dropped_books": [
        {
          "title": "我在民国续费人生",
          "intro": "【民国+金手指签到+轻松+微群像+青葱岁月+发家致富+背景板男主】 纪少微穿进自己氪过的民国游戏里，月卡只剩六天。不续费，就抹杀。 别人穿游戏是谈恋爱，她穿游戏是搞钱续命。 赛马场押冷门，陆宅晚宴当众"
        }
      ],
      "top_risers": [
        {
          "title": "闪婚，真千金嫁给了军阀大佬",
          "change": "+3"
        },
        {
          "title": "军阀养女：狼崽子的白月光是姐姐",
          "change": "+2"
        },
        {
          "title": "开局1937年：她一心只想求死",
          "change": "+2"
        }
      ],
      "top_fallers": [
        {
          "title": "穿成军统外勤后我杀疯了",
          "change": "-5"
        }
      ],
      "reads_growth": [
        {
          "title": "穿越民国，获得每日签到系统",
          "growth": "+4000"
        },
        {
          "title": "麻将特工",
          "growth": "+1008"
        },
        {
          "title": "人间正道是沧桑：四十年来家国",
          "growth": "+825"
        }
      ],
      "summary": "**🔥 题材趋势** 现代思维碰撞旧时代仍是核心卖点，分化出“带系统/直播强国”的高概念路线与“军阀虐恋+追妻火葬场”的传统言情路线，前者更易获得读者共鸣与讨论度。\n**📖 读者偏好** 读者迷恋铁血军阀为爱低头或冷面少帅追妻的强反差情节。同时，一种新趋势是女主必须拥有独立事业或现代硬核技能，不再满足于做旧时代的金丝雀。\n**🆕 新上榜作品** 《穿回四十年代逃荒去上海》以种田经营风入榜，说明在苦难题材下开拓“生活流”叙事，满足读者末日囤货与建设心理，正逐渐打开空间。\n**📉 掉出榜单** 《我在民国续费人生》因侧重游戏化经营，在情感浓度和戏剧冲突上稍弱，被同类但情感更激烈的作品挤下，说明该分类用户更重故事内的情感满足。\n**💡 值得关注** 谍战元素与“华夏直播”新物种热度持续，《掉马后，铁血少帅眼红了》等“掉马甲”设定与女强人设高度绑定，是制造转折和爽点的万金油。"
    }
  }
}